{
  "audio_features": [
    null,
    {
      "danceability": 0.452,
      "energy": 0.341,
      "key": 8,
      "loudness": -13.257,
      "mode": 1,
      "speechiness": 0.0619,
      "acousticness": 0.877,
      "instrumentalness": 0.00177,
      "liveness": 0.14,
      "valence": 0.587,
      "tempo": 107.496,
      "type": "audio_features",
      "id": "5HeEJbaS7V9Ft7gfq8uRGi",
      "uri": "spotify:track:5HeEJbaS7V9Ft7gfq8uRGi",
      "track_href": "https://api.spotify.com/v1/tracks/5HeEJbaS7V9Ft7gfq8uRGi",
      "analysis_url": "https://api.spotify.com/v1/audio-analysis/5HeEJbaS7V9Ft7gfq8uRGi",
      "duration_ms": 325827,
      "time_signature": 3
    },
    {
      "danceability": 0.622,
      "energy": 0.886,
      "key": 4,
      "loudness": -4.828,
      "mode": 1,
      "speechiness": 0.0883,
      "acousticness": 0.0107,
      "instrumentalness": 0,
      "liveness": 0.354,
      "valence": 0.603,
      "tempo": 127.969,
      "type": "audio_features",
      "id": "6ns2oVPYMdlftelbSHlzvO",
      "uri": "spotify:track:6ns2oVPYMdlftelbSHlzvO",
      "track_href": "https://api.spotify.com/v1/tracks/6ns2oVPYMdlftelbSHlzvO",
      "analysis_url": "https://api.spotify.com/v1/audio-analysis/6ns2oVPYMdlftelbSHlzvO",
      "duration_ms": 220920,
      "time_signature": 4
    },
    {
      "danceability": 0.787,
      "energy": 0.625,
      "key": 3,
      "loudness": -4.194,
      "mode": 0,
      "speechiness": 0.0543,
      "acousticness": 0.293,
      "instrumentalness": 0,
      "liveness": 0.15,
      "valence": 0.215,
      "tempo": 123.983,
      "type": "audio_features",
      "id": "7sO0dVFCfixpLshm4daMH3",
      "uri": "spotify:track:7sO0dVFCfixpLshm4daMH3",
      "track_href": "https://api.spotify.com/v1/tracks/7sO0dVFCfixpLshm4daMH3",
      "analysis_url": "https://api.spotify.com/v1/audio-analysis/7sO0dVFCfixpLshm4daMH3",
      "duration_ms": 248506,
      "time_signature": 4
    },
    {
      "danceability": 0.423,
      "energy": 0.38,
      "key": 0,
      "loudness": -10.254,
      "mode": 1,
      "speechiness": 0.0262,
      "acousticness": 0.00216,
      "instrumentalness": 0.832,
      "liveness": 0.0957,
      "valence": 0.0432,
      "tempo": 87.029,
      "type": "audio_features",
      "id": "27gb40S6AIpP5lrhLxlfXj",
      "uri": "spotify:track:27gb40S6AIpP5lrhLxlfXj",
      "track_href": "https://api.spotify.com/v1/tracks/27gb40S6AIpP5lrhLxlfXj",
      "analysis_url": "https://api.spotify.com/v1/audio-analysis/27gb40S6AIpP5lrhLxlfXj",
      "duration_ms": 237333,
      "time_signature": 3
    },
    {
      "danceability": 0.467,
      "energy": 0.492,
      "key": 11,
      "loudness": -10.767,
      "mode": 1,
      "speechiness": 0.0296,
      "acousticness": 0.836,
      "instrumentalness": 2.48e-05,
      "liveness": 0.15,
      "valence": 0.188,
      "tempo": 137.162,
      "type": "audio_features",
      "id": "321jLsfufuG8Ot8GsYffdm",
      "uri": "spotify:track:321jLsfufuG8Ot8GsYffdm",
      "track_href": "https://api.spotify.com/v1/tracks/321jLsfufuG8Ot8GsYffdm",
      "analysis_url": "https://api.spotify.com/v1/audio-analysis/321jLsfufuG8Ot8GsYffdm",
      "duration_ms": 264680,
      "time_signature": 4
    },
    {
      "danceability": 0.386,
      "energy": 0.973,
      "key": 10,
      "loudness": -5.471,
      "mode": 1,
      "speechiness": 0.135,
      "acousticness": 0.000794,
      "instrumentalness": 1.63e-06,
      "liveness": 0.119,
      "valence": 0.367,
      "tempo": 165.044,
      "type": "audio_features",
      "id": "296Cm8FMjrIGdI60VTuaTS",
      "uri": "spotify:track:296Cm8FMjrIGdI60VTuaTS",
      "track_href": "https://api.spotify.com/v1/tracks/296Cm8FMjrIGdI60VTuaTS",
      "analysis_url": "https://api.spotify.com/v1/audio-analysis/296Cm8FMjrIGdI60VTuaTS",
      "duration_ms": 227307,
      "time_signature": 4
    },
    {
      "danceability": 0.239,
      "energy": 0.507,
      "key": 1,
      "loudness": -6.662,
      "mode": 1,
      "speechiness": 0.0695,
      "acousticness": 0.732,
      "instrumentalness": 0,
      "liveness": 0.329,
      "valence": 0.361,
      "tempo": 80.4,
      "type": "audio_features",
      "id": "5E1mVJ10v4oLbcdlxYZNXv",
      "uri": "spotify:track:5E1mVJ10v4oLbcdlxYZNXv",
      "track_href": "https://api.spotify.com/v1/tracks/5E1mVJ10v4oLbcdlxYZNXv",
      "analysis_url": "https://api.spotify.com/v1/audio-analysis/5E1mVJ10v4oLbcdlxYZNXv",
      "duration_ms": 351987,
      "time_signature": 4
    },
    {
      "danceability": 0.382,
      "energy": 0.962,
      "key": 0,
      "loudness": -5.715,
      "mode": 1,
      "speechiness": 0.108,
      "acousticness": 6.91e-05,
      "instrumentalness": 0.000307,
      "liveness": 0.111,
      "valence": 0.369,
      "tempo": 119.502,
      "type": "audio_features",
      "id": "5Ijszsp089kQRXHMBClTQd",
      "uri": "spotify:track:5Ijszsp089kQRXHMBClTQd",
      "track_href": "https://api.spotify.com/v1/tracks/5Ijszsp089kQRXHMBClTQd",
      "analysis_url": "https://api.spotify.com/v1/audio-analysis/5Ijszsp089kQRXHMBClTQd",
      "duration_ms": 171040,
      "time_signature": 4
    },
    {
      "danceability": 0.638,
      "energy": 0.508,
      "key": 2,
      "loudness": -9.576,
      "mode": 1,
      "speechiness": 0.0553,
      "acousticness": 0.56,
      "instrumentalness": 0,
      "liveness": 0.138,
      "valence": 0.245,
      "tempo": 144.012,
      "type": "audio_features",
      "id": "6dckQk525bZ07rP70M2swG",
      "uri": "spotify:track:6dckQk525bZ07rP70M2swG",
      "track_href": "https://api.spotify.com/v1/tracks/6dckQk525bZ07rP70M2swG",
      "analysis_url": "https://api.spotify.com/v1/audio-analysis/6dckQk525bZ07rP70M2swG",
      "duration_ms": 221910,
      "time_signature": 4
    },
    {
      "danceability": 0.325,
      "energy": 0.952,
      "key": 7,
      "loudness": -6.78,
      "mode": 1,
      "speechiness": 0.233,
      "acousticness": 0.0457,
      "instrumentalness": 0,
      "liveness": 0.268,
      "valence": 0.316,
      "tempo": 165.187,
      "type": "audio_features",
      "id": "3mbo8Kd5O9LGLzRb2b1BMx",
      "uri": "spotify:track:3mbo8Kd5O9LGLzRb2b1BMx",
      "track_href": "https://api.spotify.com/v1/tracks/3mbo8Kd5O9LGLzRb2b1BMx",
      "analysis_url": "https://api.spotify.com/v1/audio-analysis/3mbo8Kd5O9LGLzRb2b1BMx",
      "duration_ms": 172427,
      "time_signature": 4
    },
    {
      "danceability": 0.832,
      "energy": 0.552,
      "key": 2,
      "loudness": -10.067,
      "mode": 1,
      "speechiness": 0.0771,
      "acousticness": 0.00727,
      "instrumentalness": 0.235,
      "liveness": 0.0943,
      "valence": 0.684,
      "tempo": 120.001,
      "type": "audio_features",
      "id": "66nHwYkmizcFzp1nbAE9UZ",
      "uri": "spotify:track:66nHwYkmizcFzp1nbAE9UZ",
      "track_href": "https://api.spotify.com/v1/tracks/66nHwYkmizcFzp1nbAE9UZ",
      "analysis_url": "https://api.spotify.com/v1/audio-analysis/66nHwYkmizcFzp1nbAE9UZ",
      "duration_ms": 313413,
      "time_signature": 4
    },
    {
      "danceability": 0.343,
      "energy": 0.977,
      "key": 2,
      "loudness": -4.993,
      "mode": 1,
      "speechiness": 0.0579,
      "acousticness": 0.00455,
      "instrumentalness": 0.0197,
      "liveness": 0.0948,
      "valence": 0.727,
      "tempo": 166.664,
      "type": "audio_features",
      "id": "4m0Vgr48VFaMYw0Sp1ozJu",
      "uri": "spotify:track:4m0Vgr48VFaMYw0Sp1ozJu",
      "track_href": "https://api.spotify.com/v1/tracks/4m0Vgr48VFaMYw0Sp1ozJu",
      "analysis_url": "https://api.spotify.com/v1/audio-analysis/4m0Vgr48VFaMYw0Sp1ozJu",
      "duration_ms": 242293,
      "time_signature": 4
    },
    {
      "danceability": 0.504,
      "energy": 0.925,
      "key": 7,
      "loudness": -4.148,
      "mode": 1,
      "speechiness": 0.119,
      "acousticness": 4.76e-06,
      "instrumentalness": 0.926,
      "liveness": 0.0895,
      "valence": 0.77,
      "tempo": 149.906,
      "type": "audio_features",
      "id": "1LdYdHyVuSh399v73Q82Y7",
      "uri": "spotify:track:1LdYdHyVuSh399v73Q82Y7",
      "track_href": "https://api.spotify.com/v1/tracks/1LdYdHyVuSh399v73Q82Y7",
      "analysis_url": "https://api.spotify.com/v1/audio-analysis/1LdYdHyVuSh399v73Q82Y7",
      "duration_ms": 213229,
      "time_signature": 4
    },
    {
      "danceability": 0.518,
      "energy": 0.611,
      "key": 4,
      "loudness": -4.407,
      "mode": 1,
      "speechiness": 0.028,
      "acousticness": 0.564,
      "instrumentalness": 1.28e-06,
      "liveness": 0.165,
      "valence": 0.668,
      "tempo": 87.611,
      "type": "audio_features",
      "id": "2Ef6uEWmlcCSaZD3hBpkIF",
      "uri": "spotify:track:2Ef6uEWmlcCSaZD3hBpkIF",
      "track_href": "https://api.spotify.com/v1/tracks/2Ef6uEWmlcCSaZD3hBpkIF",
      "analysis_url": "https://api.spotify.com/v1/audio-analysis/2Ef6uEWmlcCSaZD3hBpkIF",
      "duration_ms": 166557,
      "time_signature": 4
    },
    {
      "danceability": 0.483,
      "energy": 0.762,
      "key": 5,
      "loudness": -4.714,
      "mode": 1,
      "speechiness": 0.0943,
      "acousticness": 0.646,
      "instrumentalness": 0,
      "liveness": 0.163,
      "valence": 0.547,
      "tempo": 76.033,
      "type": "audio_features",
      "id": "0EsNP48ZxnuQx303EcckwI",
      "uri": "spotify:track:0EsNP48ZxnuQx303EcckwI",
      "track_href": "https://api.spotify.com/v1/tracks/0EsNP48ZxnuQx303EcckwI",
      "analysis_url": "https://api.spotify.com/v1/audio-analysis/0EsNP48ZxnuQx303EcckwI",
      "duration_ms": 218240,
      "time_signature": 4
    },
    {
      "danceability": 0.773,
      "energy": 0.936,
      "key": 0,
      "loudness": -5.215,
      "mode": 1,
      "speechiness": 0.0999,
      "acousticness": 0.172,
      "instrumentalness": 0.135,
      "liveness": 0.334,
      "valence": 0.927,
      "tempo": 76.484,
      "type": "audio_features",
      "id": "5FXinDq5ECCkhl1fHhhB90",
      "uri": "spotify:track:5FXinDq5ECCkhl1fHhhB90",
      "track_href": "https://api.spotify.com/v1/tracks/5FXinDq5ECCkhl1fHhhB90",
      "analysis_url": "https://api.spotify.com/v1/audio-analysis/5FXinDq5ECCkhl1fHhhB90",
      "duration_ms": 245960,
      "time_signature": 4
    },
    {
      "danceability": 0.532,
      "energy": 0.203,
      "key": 9,
      "loudness": -8.524,
      "mode": 0,
      "speechiness": 0.0668,
      "acousticness": 0.829,
      "instrumentalness": 0,
      "liveness": 0.108,
      "valence": 0.543,
      "tempo": 89.646,
      "type": "audio_features",
      "id": "4zzi2eD2cEPpQ3a307mPPj",
      "uri": "spotify:track:4zzi2eD2cEPpQ3a307mPPj",
      "track_href": "https://api.spotify.com/v1/tracks/4zzi2eD2cEPpQ3a307mPPj",
      "analysis_url": "https://api.spotify.com/v1/audio-analysis/4zzi2eD2cEPpQ3a307mPPj",
      "duration_ms": 259920,
      "time_signature": 4
    },
    {
      "danceability": 0.368,
      "energy": 0.986,
      "key": 7,
      "loudness": -5.016,
      "mode": 1,
      "speechiness": 0.0533,
      "acousticness": 0.00323,
      "instrumentalness": 6.61e-06,
      "liveness": 0.0787,
      "valence": 0.452,
      "tempo": 165.902,
      "type": "audio_features",
      "id": "0zwjhaBWQEs7LUkuIZFRtl",
      "uri": "spotify:track:0zwjhaBWQEs7LUkuIZFRtl",
      "track_href": "https://api.spotify.com/v1/tracks/0zwjhaBWQEs7LUkuIZFRtl",
      "analysis_url": "https://api.spotify.com/v1/audio-analysis/0zwjhaBWQEs7LUkuIZFRtl",
      "duration_ms": 154040,
      "time_signature": 4
    },
    {
      "danceability": 0.689,
      "energy": 0.711,
      "key": 8,
      "loudness": -6.572,
      "mode": 1,
      "speechiness": 0.122,
      "acousticness": 0.0311,
      "instrumentalness": 0,
      "liveness": 0.116,
      "valence": 0.398,
      "tempo": 97.992,
      "type": "audio_features",
      "id": "2amEGukf72WmlPCXujlRgl",
      "uri": "spotify:track:2amEGukf72WmlPCXujlRgl",
      "track_href": "https://api.spotify.com/v1/tracks/2amEGukf72WmlPCXujlRgl",
      "analysis_url": "https://api.spotify.com/v1/audio-analysis/2amEGukf72WmlPCXujlRgl",
      "duration_ms": 227773,
      "time_signature": 4
    },
    {
      "danceability": 0.607,
      "energy": 0.595,
      "key": 7,
      "loudness": -9.237,
      "mode": 0,
      "speechiness": 0.0542,
      "acousticness": 0.161,
      "instrumentalness": 0.0188,
      "liveness": 0.184,
      "valence": 0.581,
      "tempo": 180.982,
      "type": "audio_features",
      "id": "4bNKvePgcSeo9eQM2yIbVE",
      "uri": "spotify:track:4bNKvePgcSeo9eQM2yIbVE",
      "track_href": "https://api.spotify.com/v1/tracks/4bNKvePgcSeo9eQM2yIbVE",
      "analysis_url": "https://api.spotify.com/v1/audio-analysis/4bNKvePgcSeo9eQM2yIbVE",
      "duration_ms": 278773,
      "time_signature": 4
    },
    {
      "danceability": 0.59,
      "energy": 0.872,
      "key": 1,
      "loudness": -6.007,
      "mode": 1,
      "speechiness": 0.377,
      "acousticness": 0.0151,
      "instrumentalness": 2.44e-06,
      "liveness": 0.295,
      "valence": 0.617,
      "tempo": 84.332,
      "type": "audio_features",
      "id": "1oyz68YDgZbEdQ3lBDQROR",
      "uri": "spotify:track:1oyz68YDgZbEdQ3lBDQROR",
      "track_href": "https://api.spotify.com/v1/tracks/1oyz68YDgZbEdQ3lBDQROR",
      "analysis_url": "https://api.spotify.com/v1/audio-analysis/1oyz68YDgZbEdQ3lBDQROR",
      "duration_ms": 221173,
      "time_signature": 4
    },
    {
      "danceability": 0.472,
      "energy": 0.988,
      "key": 9,
      "loudness": -3.975,
      "mode": 1,
      "speechiness": 0.0987,
      "acousticness": 2.02e-05,
      "instrumentalness": 0.00591,
      "liveness": 0.123,
      "valence": 0.559,
      "tempo": 98.5,
      "type": "audio_features",
      "id": "0okEeHYqnA5z3mDmOtz4Az",
      "uri": "spotify:track:0okEeHYqnA5z3mDmOtz4Az",
      "track_href": "https://api.spotify.com/v1/tracks/0okEeHYqnA5z3mDmOtz4Az",
      "analysis_url": "https://api.spotify.com/v1/audio-analysis/0okEeHYqnA5z3mDmOtz4Az",
      "duration_ms": 169173,
      "time_signature": 4
    },
    {
      "danceability": 0.543,
      "energy": 0.826,
      "key": 10,
      "loudness": -3.836,
      "mode": 1,
      "speechiness": 0.0314,
      "acousticness": 0.106,
      "instrumentalness": 0,
      "liveness": 0.253,
      "valence": 0.461,
      "tempo": 91.954,
      "type": "audio_features",
      "id": "7uar5Z1K9GRtOCJYgszTBK",
      "uri": "spotify:track:7uar5Z1K9GRtOCJYgszTBK",
      "track_href": "https://api.spotify.com/v1/tracks/7uar5Z1K9GRtOCJYgszTBK",
      "analysis_url": "https://api.spotify.com/v1/audio-analysis/7uar5Z1K9GRtOCJYgszTBK",
      "duration_ms": 244200,
      "time_signature": 4
    },
    {
      "danceability": 0.474,
      "energy": 0.442,
      "key": 11,
      "loudness": -15.049,
      "mode": 0,
      "speechiness": 0.0423,
      "acousticness": 0.000146,
      "instrumentalness": 0.000212,
      "liveness": 0.213,
      "valence": 0.773,
      "tempo": 118.362,
      "type": "audio_features",
      "id": "0B3hFXFOlbIPt942VGdNfb",
      "uri": "spotify:track:0B3hFXFOlbIPt942VGdNfb",
      "track_href": "https://api.spotify.com/v1/tracks/0B3hFXFOlbIPt942VGdNfb",
      "analysis_url": "https://api.spotify.com/v1/audio-analysis/0B3hFXFOlbIPt942VGdNfb",
      "duration_ms": 237507,
      "time_signature": 4
    },
    {
      "danceability": 0.643,
      "energy": 0.726,
      "key": 0,
      "loudness": -8.973,
      "mode": 1,
      "speechiness": 0.0529,
      "acousticness": 0.00065,
      "instrumentalness": 0.0108,
      "liveness": 0.0801,
      "valence": 0.553,
      "tempo": 94.026,
      "type": "audio_features",
      "id": "464XjjRcO8no1YY9amYKbv",
      "uri": "spotify:track:464XjjRcO8no1YY9amYKbv",
      "track_href": "https://api.spotify.com/v1/tracks/464XjjRcO8no1YY9amYKbv",
      "analysis_url": "https://api.spotify.com/v1/audio-analysis/464XjjRcO8no1YY9amYKbv",
      "duration_ms": 422173,
      "time_signature": 4
    },
    {
      "danceability": 0.925,
      "energy": 0.443,
      "key": 1,
      "loudness": -8.216,
      "mode": 1,
      "speechiness": 0.264,
      "acousticness": 0.0172,
      "instrumentalness": 0,
      "liveness": 0.276,
      "valence": 0.35,
      "tempo": 136.078,
      "type": "audio_features",
      "id": "2bjwRfXMk4uRgOD9IBYl9h",
      "uri": "spotify:track:2bjwRfXMk4uRgOD9IBYl9h",
      "track_href": "https://api.spotify.com/v1/tracks/2bjwRfXMk4uRgOD9IBYl9h",
      "analysis_url": "https://api.spotify.com/v1/audio-analysis/2bjwRfXMk4uRgOD9IBYl9h",
      "duration_ms": 236615,
      "time_signature": 4
    },
    {
      "danceability": 0.772,
      "energy": 0.586,
      "key": 10,
      "loudness": -10.434,
      "mode": 0,
      "speechiness": 0.301,
      "acousticness": 0.0234,
      "instrumentalness": 0.000722,
      "liveness": 0.0562,
      "valence": 0.643,
      "tempo": 85.068,
      "type": "audio_features",
      "id": "2oLwDI8tZUOh6SmTMRRfKs",
      "uri": "spotify:track:2oLwDI8tZUOh6SmTMRRfKs",
      "track_href": "https://api.spotify.com/v1/tracks/2oLwDI8tZUOh6SmTMRRfKs",
      "analysis_url": "https://api.spotify.com/v1/audio-analysis/2oLwDI8tZUOh6SmTMRRfKs",
      "duration_ms": 265200,
      "time_signature": 4
    },
    {
      "danceability": 0.392,
      "energy": 0.697,
      "key": 1,
      "loudness": -4.96,
      "mode": 1,
      "speechiness": 0.0454,
      "acousticness": 0.0738,
      "instrumentalness": 1.02e-06,
      "liveness": 0.281,
      "valence": 0.335,
      "tempo": 153.021,
      "type": "audio_features",
      "id": "0rNeeuctfOk0dpF35sz0Dg",
      "uri": "spotify:track:0rNeeuctfOk0dpF35sz0Dg",
      "track_href": "https://api.spotify.com/v1/tracks/0rNeeuctfOk0dpF35sz0Dg",
      "analysis_url": "https://api.spotify.com/v1/audio-analysis/0rNeeuctfOk0dpF35sz0Dg",
      "duration_ms": 196760,
      "time_signature": 4
    },
    {
      "danceability": 0.452,
      "energy": 0.571,
      "key": 7,
      "loudness": -3.992,
      "mode": 1,
      "speechiness": 0.0359,
      "acousticness": 0.25,
      "instrumentalness": 0,
      "liveness": 0.114,
      "valence": 0.327,
      "tempo": 169.899,
      "type": "audio_features",
      "id": "1NpDnkQO0yWxTtntrC0UNz",
      "uri": "spotify:track:1NpDnkQO0yWxTtntrC0UNz",
      "track_href": "https://api.spotify.com/v1/tracks/1NpDnkQO0yWxTtntrC0UNz",
      "analysis_url": "https://api.spotify.com/v1/audio-analysis/1NpDnkQO0yWxTtntrC0UNz",
      "duration_ms": 251600,
      "time_signature": 4
    },
    {
      "danceability": 0.905,
      "energy": 0.604,
      "key": 4,
      "loudness": -7.433,
      "mode": 0,
      "speechiness": 0.0413,
      "acousticness": 0.149,
      "instrumentalness": 9.24e-05,
      "liveness": 0.0523,
      "valence": 0.899,
      "tempo": 109.196,
      "type": "audio_features",
      "id": "7BeV8s7R68eqPelMmvp5tu",
      "uri": "spotify:track:7BeV8s7R68eqPelMmvp5tu",
      "track_href": "https://api.spotify.com/v1/tracks/7BeV8s7R68eqPelMmvp5tu",
      "analysis_url": "https://api.spotify.com/v1/audio-analysis/7BeV8s7R68eqPelMmvp5tu",
      "duration_ms": 242400,
      "time_signature": 4
    },
    {
      "danceability": 0.515,
      "energy": 0.871,
      "key": 9,
      "loudness": -4.812,
      "mode": 0,
      "speechiness": 0.0677,
      "acousticness": 0.0531,
      "instrumentalness": 0,
      "liveness": 0.056,
      "valence": 0.292,
      "tempo": 134.013,
      "type": "audio_features",
      "id": "00gwlKTiWvu6xqvsWy7ehA",
      "uri": "spotify:track:00gwlKTiWvu6xqvsWy7ehA",
      "track_href": "https://api.spotify.com/v1/tracks/00gwlKTiWvu6xqvsWy7ehA",
      "analysis_url": "https://api.spotify.com/v1/audio-analysis/00gwlKTiWvu6xqvsWy7ehA",
      "duration_ms": 227847,
      "time_signature": 4
    },
    {
      "danceability": 0.578,
      "energy": 0.471,
      "key": 4,
      "loudness": -7.27,
      "mode": 1,
      "speechiness": 0.0289,
      "acousticness": 0.368,
      "instrumentalness": 0,
      "liveness": 0.159,
      "valence": 0.532,
      "tempo": 133.061,
      "type": "audio_features",
      "id": "4GiXBCUF7H6YfNQsnBRIzl",
      "uri": "spotify:track:4GiXBCUF7H6YfNQsnBRIzl",
      "track_href": "https://api.spotify.com/v1/tracks/4GiXBCUF7H6YfNQsnBRIzl",
      "analysis_url": "https://api.spotify.com/v1/audio-analysis/4GiXBCUF7H6YfNQsnBRIzl",
      "duration_ms": 196707,
      "time_signature": 4
    },
    {
      "danceability": 0.497,
      "energy": 0.882,
      "key": 8,
      "loudness": -5.621,
      "mode": 1,
      "speechiness": 0.0412,
      "acousticness": 0.00151,
      "instrumentalness": 7.11e-06,
      "liveness": 0.139,
      "valence": 0.922,
      "tempo": 76.481,
      "type": "audio_features",
      "id": "6szw2Y2ywtth0oc7ODN3Tz",
      "uri": "spotify:track:6szw2Y2ywtth0oc7ODN3Tz",
      "track_href": "https://api.spotify.com/v1/tracks/6szw2Y2ywtth0oc7ODN3Tz",
      "analysis_url": "https://api.spotify.com/v1/audio-analysis/6szw2Y2ywtth0oc7ODN3Tz",
      "duration_ms": 206467,
      "time_signature": 4
    },
    {
      "danceability": 0.732,
      "energy": 0.78,
      "key": 3,
      "loudness": -3.768,
      "mode": 0,
      "speechiness": 0.0509,
      "acousticness": 0.0476,
      "instrumentalness": 0.249,
      "liveness": 0.217,
      "valence": 0.735,
      "tempo": 100.015,
      "type": "audio_features",
      "id": "0LTcxo6kppNpE1A8GJAh7B",
      "uri": "spotify:track:0LTcxo6kppNpE1A8GJAh7B",
      "track_href": "https://api.spotify.com/v1/tracks/0LTcxo6kppNpE1A8GJAh7B",
      "analysis_url": "https://api.spotify.com/v1/audio-analysis/0LTcxo6kppNpE1A8GJAh7B",
      "duration_ms": 319203,
      "time_signature": 4
    },
    {
      "danceability": 0.802,
      "energy": 0.919,
      "key": 0,
      "loudness": -3.107,
      "mode": 1,
      "speechiness": 0.0592,
      "acousticness": 0.00011,
      "instrumentalness": 0.105,
      "liveness": 0.107,
      "valence": 0.398,
      "tempo": 124.994,
      "type": "audio_features",
      "id": "6FQt64CUdNfQMWXEcpZtAt",
      "uri": "spotify:track:6FQt64CUdNfQMWXEcpZtAt",
      "track_href": "https://api.spotify.com/v1/tracks/6FQt64CUdNfQMWXEcpZtAt",
      "analysis_url": "https://api.spotify.com/v1/audio-analysis/6FQt64CUdNfQMWXEcpZtAt",
      "duration_ms": 278400,
      "time_signature": 4
    },
    {
      "danceability": 0.595,
      "energy": 0.901,
      "key": 8,
      "loudness": -3.707,
      "mode": 0,
      "speechiness": 0.032,
      "acousticness": 0.000642,
      "instrumentalness": 0.000145,
      "liveness": 0.101,
      "valence": 0.641,
      "tempo": 121.932,
      "type": "audio_features",
      "id": "6hZdnZ9V1rGDDWbcMJ2OBl",
      "uri": "spotify:track:6hZdnZ9V1rGDDWbcMJ2OBl",
      "track_href": "https://api.spotify.com/v1/tracks/6hZdnZ9V1rGDDWbcMJ2OBl",
      "analysis_url": "https://api.spotify.com/v1/audio-analysis/6hZdnZ9V1rGDDWbcMJ2OBl",
      "duration_ms": 195227,
      "time_signature": 4
    },
    {
      "danceability": 0.286,
      "energy": 0.892,
      "key": 5,
      "loudness": -3.767,
      "mode": 0,
      "speechiness": 0.0731,
      "acousticness": 0.000561,
      "instrumentalness": 0.00016,
      "liveness": 0.157,
      "valence": 0.374,
      "tempo": 172.016,
      "type": "audio_features",
      "id": "6eKEJZFWllRX4UALhPU967",
      "uri": "spotify:track:6eKEJZFWllRX4UALhPU967",
      "track_href": "https://api.spotify.com/v1/tracks/6eKEJZFWllRX4UALhPU967",
      "analysis_url": "https://api.spotify.com/v1/audio-analysis/6eKEJZFWllRX4UALhPU967",
      "duration_ms": 331187,
      "time_signature": 4
    },
    {
      "danceability": 0.65,
      "energy": 0.975,
      "key": 4,
      "loudness": -4.968,
      "mode": 0,
      "speechiness": 0.0686,
      "acousticness": 0.000411,
      "instrumentalness": 0.82,
      "liveness": 0.105,
      "valence": 0.309,
      "tempo": 100.017,
      "type": "audio_features",
      "id": "0ARdUFG6P2HR1mQvFoBJmq",
      "uri": "spotify:track:0ARdUFG6P2HR1mQvFoBJmq",
      "track_href": "https://api.spotify.com/v1/tracks/0ARdUFG6P2HR1mQvFoBJmq",
      "analysis_url": "https://api.spotify.com/v1/audio-analysis/0ARdUFG6P2HR1mQvFoBJmq",
      "duration_ms": 235269,
      "time_signature": 4
    },
    {
      "danceability": 0.794,
      "energy": 0.848,
      "key": 9,
      "loudness": -4.294,
      "mode": 1,
      "speechiness": 0.14,
      "acousticness": 0.0354,
      "instrumentalness": 2.4e-05,
      "liveness": 0.19,
      "valence": 0.565,
      "tempo": 121.989,
      "type": "audio_features",
      "id": "3Bhnf6fhi3m28ibUJZepSh",
      "uri": "spotify:track:3Bhnf6fhi3m28ibUJZepSh",
      "track_href": "https://api.spotify.com/v1/tracks/3Bhnf6fhi3m28ibUJZepSh",
      "analysis_url": "https://api.spotify.com/v1/audio-analysis/3Bhnf6fhi3m28ibUJZepSh",
      "duration_ms": 338484,
      "time_signature": 4
    },
    {
      "danceability": 0.505,
      "energy": 0.313,
      "key": 6,
      "loudness": -8.244,
      "mode": 1,
      "speechiness": 0.0309,
      "acousticness": 0.624,
      "instrumentalness": 0,
      "liveness": 0.156,
      "valence": 0.303,
      "tempo": 136.074,
      "type": "audio_features",
      "id": "795SM7LI7D1UQ4aguJHBK9",
      "uri": "spotify:track:795SM7LI7D1UQ4aguJHBK9",
      "track_href": "https://api.spotify.com/v1/tracks/795SM7LI7D1UQ4aguJHBK9",
      "analysis_url": "https://api.spotify.com/v1/audio-analysis/795SM7LI7D1UQ4aguJHBK9",
      "duration_ms": 184560,
      "time_signature": 4
    },
    {
      "danceability": 0.434,
      "energy": 0.928,
      "key": 9,
      "loudness": -3.575,
      "mode": 0,
      "speechiness": 0.0605,
      "acousticness": 0.00277,
      "instrumentalness": 0,
      "liveness": 0.053,
      "valence": 0.336,
      "tempo": 143.155,
      "type": "audio_features",
      "id": "5yNw7KhDPNO8g3Wfm7Eamj",
      "uri": "spotify:track:5yNw7KhDPNO8g3Wfm7Eamj",
      "track_href": "https://api.spotify.com/v1/tracks/5yNw7KhDPNO8g3Wfm7Eamj",
      "analysis_url": "https://api.spotify.com/v1/audio-analysis/5yNw7KhDPNO8g3Wfm7Eamj",
      "duration_ms": 248600,
      "time_signature": 4
    },
    {
      "danceability": 0.755,
      "energy": 0.64,
      "key": 0,
      "loudness": -6.026,
      "mode": 0,
      "speechiness": 0.268,
      "acousticness": 0.27,
      "instrumentalness": 0,
      "liveness": 0.121,
      "valence": 0.573,
      "tempo": 75.027,
      "type": "audio_features",
      "id": "45n4xViJwwJCMKUyHXTCPJ",
      "uri": "spotify:track:45n4xViJwwJCMKUyHXTCPJ",
      "track_href": "https://api.spotify.com/v1/tracks/45n4xViJwwJCMKUyHXTCPJ",
      "analysis_url": "https://api.spotify.com/v1/audio-analysis/45n4xViJwwJCMKUyHXTCPJ",
      "duration_ms": 238919,
      "time_signature": 4
    },
    {
      "danceability": 0.564,
      "energy": 0.615,
      "key": 9,
      "loudness": -7.977,
      "mode": 0,
      "speechiness": 0.0503,
      "acousticness": 0.186,
      "instrumentalness": 0.757,
      "liveness": 0.0682,
      "valence": 0.35,
      "tempo": 99.925,
      "type": "audio_features",
      "id": "3Utue3RvDoFagRE5bYlQL5",
      "uri": "spotify:track:3Utue3RvDoFagRE5bYlQL5",
      "track_href": "https://api.spotify.com/v1/tracks/3Utue3RvDoFagRE5bYlQL5",
      "analysis_url": "https://api.spotify.com/v1/audio-analysis/3Utue3RvDoFagRE5bYlQL5",
      "duration_ms": 224987,
      "time_signature": 5
    },
    {
      "danceability": 0.607,
      "energy": 0.609,
      "key": 7,
      "loudness": -7.332,
      "mode": 1,
      "speechiness": 0.026,
      "acousticness": 0.235,
      "instrumentalness": 0,
      "liveness": 0.358,
      "valence": 0.57,
      "tempo": 130.09,
      "type": "audio_features",
      "id": "5o6sSAGtypSJgErN0IOKYm",
      "uri": "spotify:track:5o6sSAGtypSJgErN0IOKYm",
      "track_href": "https://api.spotify.com/v1/tracks/5o6sSAGtypSJgErN0IOKYm",
      "analysis_url": "https://api.spotify.com/v1/audio-analysis/5o6sSAGtypSJgErN0IOKYm",
      "duration_ms": 234240,
      "time_signature": 4
    },
    {
      "danceability": 0.532,
      "energy": 0.868,
      "key": 3,
      "loudness": -4.23,
      "mode": 0,
      "speechiness": 0.0908,
      "acousticness": 0.011,
      "instrumentalness": 0,
      "liveness": 0.0584,
      "valence": 0.529,
      "tempo": 110.127,
      "type": "audio_features",
      "id": "5eTNdkstwKaNahHf41fJ9u",
      "uri": "spotify:track:5eTNdkstwKaNahHf41fJ9u",
      "track_href": "https://api.spotify.com/v1/tracks/5eTNdkstwKaNahHf41fJ9u",
      "analysis_url": "https://api.spotify.com/v1/audio-analysis/5eTNdkstwKaNahHf41fJ9u",
      "duration_ms": 187958,
      "time_signature": 4
    },
    {
      "danceability": 0.837,
      "energy": 0.694,
      "key": 11,
      "loudness": -6.173,
      "mode": 0,
      "speechiness": 0.246,
      "acousticness": 0.193,
      "instrumentalness": 1.67e-05,
      "liveness": 0.0911,
      "valence": 0.587,
      "tempo": 95.977,
      "type": "audio_features",
      "id": "12R221x0nHDbxyLZX9HMbD",
      "uri": "spotify:track:12R221x0nHDbxyLZX9HMbD",
      "track_href": "https://api.spotify.com/v1/tracks/12R221x0nHDbxyLZX9HMbD",
      "analysis_url": "https://api.spotify.com/v1/audio-analysis/12R221x0nHDbxyLZX9HMbD",
      "duration_ms": 264160,
      "time_signature": 4
    },
    {
      "danceability": 0.395,
      "energy": 0.665,
      "key": 7,
      "loudness": -6.254,
      "mode": 1,
      "speechiness": 0.028,
      "acousticness": 0.0162,
      "instrumentalness": 0.0118,
      "liveness": 0.116,
      "valence": 0.287,
      "tempo": 162.871,
      "type": "audio_features",
      "id": "055qy9CPBFPD4PhC23cULi",
      "uri": "spotify:track:055qy9CPBFPD4PhC23cULi",
      "track_href": "https://api.spotify.com/v1/tracks/055qy9CPBFPD4PhC23cULi",
      "analysis_url": "https://api.spotify.com/v1/audio-analysis/055qy9CPBFPD4PhC23cULi",
      "duration_ms": 209600,
      "time_signature": 4
    },
    {
      "danceability": 0.601,
      "energy": 0.682,
      "key": 10,
      "loudness": -5.905,
      "mode": 1,
      "speechiness": 0.0338,
      "acousticness": 0.0856,
      "instrumentalness": 0.00384,
      "liveness": 0.132,
      "valence": 0.17,
      "tempo": 94.999,
      "type": "audio_features",
      "id": "2H8LPaY3NSjmOFMH2Rygnz",
      "uri": "spotify:track:2H8LPaY3NSjmOFMH2Rygnz",
      "track_href": "https://api.spotify.com/v1/tracks/2H8LPaY3NSjmOFMH2Rygnz",
      "analysis_url": "https://api.spotify.com/v1/audio-analysis/2H8LPaY3NSjmOFMH2Rygnz",
      "duration_ms": 211200,
      "time_signature": 4
    },
    {
      "danceability": 0.462,
      "energy": 0.919,
      "key": 10,
      "loudness": -3.595,
      "mode": 1,
      "speechiness": 0.0608,
      "acousticness": 0.0145,
      "instrumentalness": 0,
      "liveness": 0.562,
      "valence": 0.523,
      "tempo": 103.021,
      "type": "audio_features",
      "id": "6z4CTIToU7a03Rq07F9FF4",
      "uri": "spotify:track:6z4CTIToU7a03Rq07F9FF4",
      "track_href": "https://api.spotify.com/v1/tracks/6z4CTIToU7a03Rq07F9FF4",
      "analysis_url": "https://api.spotify.com/v1/audio-analysis/6z4CTIToU7a03Rq07F9FF4",
      "duration_ms": 238107,
      "time_signature": 4
    }
  ]
}
