{
  "audio_features": [
    null,
    {
      "danceability": 0.749,
      "energy": 0.717,
      "key": 4,
      "loudness": -7.544,
      "mode": 0,
      "speechiness": 0.0525,
      "acousticness": 0.476,
      "instrumentalness": 0.00252,
      "liveness": 0.111,
      "valence": 0.352,
      "tempo": 128.987,
      "type": "audio_features",
      "id": "2E3z8vSSUVEoNGOL6YTvPL",
      "uri": "spotify:track:2E3z8vSSUVEoNGOL6YTvPL",
      "track_href": "https://api.spotify.com/v1/tracks/2E3z8vSSUVEoNGOL6YTvPL",
      "analysis_url": "https://api.spotify.com/v1/audio-analysis/2E3z8vSSUVEoNGOL6YTvPL",
      "duration_ms": 275547,
      "time_signature": 4
    },
    {
      "danceability": 0.704,
      "energy": 0.644,
      "key": 0,
      "loudness": -5.543,
      "mode": 1,
      "speechiness": 0.102,
      "acousticness": 0.0226,
      "instrumentalness": 1.04e-06,
      "liveness": 0.122,
      "valence": 0.273,
      "tempo": 160.058,
      "type": "audio_features",
      "id": "0DLcjcjvUywWkPYseSdg7J",
      "uri": "spotify:track:0DLcjcjvUywWkPYseSdg7J",
      "track_href": "https://api.spotify.com/v1/tracks/0DLcjcjvUywWkPYseSdg7J",
      "analysis_url": "https://api.spotify.com/v1/audio-analysis/0DLcjcjvUywWkPYseSdg7J",
      "duration_ms": 216959,
      "time_signature": 3
    },
    {
      "danceability": 0.838,
      "energy": 0.771,
      "key": 1,
      "loudness": -3.791,
      "mode": 1,
      "speechiness": 0.244,
      "acousticness": 0.0117,
      "instrumentalness": 0,
      "liveness": 0.0853,
      "valence": 0.405,
      "tempo": 175.957,
      "type": "audio_features",
      "id": "2Xqd0wUttjueBfdcltADOv",
      "uri": "spotify:track:2Xqd0wUttjueBfdcltADOv",
      "track_href": "https://api.spotify.com/v1/tracks/2Xqd0wUttjueBfdcltADOv",
      "analysis_url": "https://api.spotify.com/v1/audio-analysis/2Xqd0wUttjueBfdcltADOv",
      "duration_ms": 245387,
      "time_signature": 4
    },
    {
      "danceability": 0.851,
      "energy": 0.789,
      "key": 11,
      "loudness": -3.812,
      "mode": 1,
      "speechiness": 0.0675,
      "acousticness": 0.0848,
      "instrumentalness": 0,
      "liveness": 0.18,
      "valence": 0.955,
      "tempo": 119.989,
      "type": "audio_features",
      "id": "6Pa2clpHusIUFEjtICP9eC",
      "uri": "spotify:track:6Pa2clpHusIUFEjtICP9eC",
      "track_href": "https://api.spotify.com/v1/tracks/6Pa2clpHusIUFEjtICP9eC",
      "analysis_url": "https://api.spotify.com/v1/audio-analysis/6Pa2clpHusIUFEjtICP9eC",
      "duration_ms": 226080,
      "time_signature": 4
    },
    {
      "danceability": 0.577,
      "energy": 0.626,
      "key": 7,
      "loudness": -7.155,
      "mode": 0,
      "speechiness": 0.0363,
      "acousticness": 0.704,
      "instrumentalness": 0.000995,
      "liveness": 0.24,
      "valence": 0.684,
      "tempo": 131.023,
      "type": "audio_features",
      "id": "0yMyPV2AwXoIJPWTivXynZ",
      "uri": "spotify:track:0yMyPV2AwXoIJPWTivXynZ",
      "track_href": "https://api.spotify.com/v1/tracks/0yMyPV2AwXoIJPWTivXynZ",
      "analysis_url": "https://api.spotify.com/v1/audio-analysis/0yMyPV2AwXoIJPWTivXynZ",
      "duration_ms": 254547,
      "time_signature": 4
    },
    {
      "danceability": 0.657,
      "energy": 0.464,
      "key": 4,
      "loudness": -7.573,
      "mode": 0,
      "speechiness": 0.0614,
      "acousticness": 0.548,
      "instrumentalness": 0,
      "liveness": 0.161,
      "valence": 0.598,
      "tempo": 75.982,
      "type": "audio_features",
      "id": "7A1uqFLf1ZogDxxQZDoZHK",
      "uri": "spotify:track:7A1uqFLf1ZogDxxQZDoZHK",
      "track_href": "https://api.spotify.com/v1/tracks/7A1uqFLf1ZogDxxQZDoZHK",
      "analysis_url": "https://api.spotify.com/v1/audio-analysis/7A1uqFLf1ZogDxxQZDoZHK",
      "duration_ms": 227067,
      "time_signature": 4
    },
    {
      "danceability": 0.51,
      "energy": 0.398,
      "key": 4,
      "loudness": -8.75,
      "mode": 0,
      "speechiness": 0.0558,
      "acousticness": 0.135,
      "instrumentalness": 3.78e-06,
      "liveness": 0.0634,
      "valence": 0.382,
      "tempo": 119.973,
      "type": "audio_features",
      "id": "01gNiOqg8u7vT90uVgOVmz",
      "uri": "spotify:track:01gNiOqg8u7vT90uVgOVmz",
      "track_href": "https://api.spotify.com/v1/tracks/01gNiOqg8u7vT90uVgOVmz",
      "analysis_url": "https://api.spotify.com/v1/audio-analysis/01gNiOqg8u7vT90uVgOVmz",
      "duration_ms": 299160,
      "time_signature": 4
    },
    {
      "danceability": 0.677,
      "energy": 0.818,
      "key": 11,
      "loudness": -7.722,
      "mode": 1,
      "speechiness": 0.0664,
      "acousticness": 0.00125,
      "instrumentalness": 0.294,
      "liveness": 0.188,
      "valence": 0.41,
      "tempo": 126.037,
      "type": "audio_features",
      "id": "7dUWdjffkQ3jEece01s2gg",
      "uri": "spotify:track:7dUWdjffkQ3jEece01s2gg",
      "track_href": "https://api.spotify.com/v1/tracks/7dUWdjffkQ3jEece01s2gg",
      "analysis_url": "https://api.spotify.com/v1/audio-analysis/7dUWdjffkQ3jEece01s2gg",
      "duration_ms": 473283,
      "time_signature": 4
    },
    {
      "danceability": 0.615,
      "energy": 0.453,
      "key": 4,
      "loudness": -8.347,
      "mode": 1,
      "speechiness": 0.0308,
      "acousticness": 0.213,
      "instrumentalness": 5.28e-05,
      "liveness": 0.142,
      "valence": 0.38,
      "tempo": 144.015,
      "type": "audio_features",
      "id": "2hhHwY2rzWLeFenIg3e6o0",
      "uri": "spotify:track:2hhHwY2rzWLeFenIg3e6o0",
      "track_href": "https://api.spotify.com/v1/tracks/2hhHwY2rzWLeFenIg3e6o0",
      "analysis_url": "https://api.spotify.com/v1/audio-analysis/2hhHwY2rzWLeFenIg3e6o0",
      "duration_ms": 323307,
      "time_signature": 4
    },
    {
      "danceability": 0.607,
      "energy": 0.861,
      "key": 10,
      "loudness": -10.461,
      "mode": 0,
      "speechiness": 0.326,
      "acousticness": 0.708,
      "instrumentalness": 0.879,
      "liveness": 0.279,
      "valence": 0.318,
      "tempo": 139.04,
      "type": "audio_features",
      "id": "63ped7sDHMOrqMFMBCTPw5",
      "uri": "spotify:track:63ped7sDHMOrqMFMBCTPw5",
      "track_href": "https://api.spotify.com/v1/tracks/63ped7sDHMOrqMFMBCTPw5",
      "analysis_url": "https://api.spotify.com/v1/audio-analysis/63ped7sDHMOrqMFMBCTPw5",
      "duration_ms": 236827,
      "time_signature": 4
    },
    {
      "danceability": 0.424,
      "energy": 0.475,
      "key": 0,
      "loudness": -8.065,
      "mode": 1,
      "speechiness": 0.034,
      "acousticness": 0.659,
      "instrumentalness": 0.00823,
      "liveness": 0.0727,
      "valence": 0.268,
      "tempo": 104.967,
      "type": "audio_features",
      "id": "4EoPPRJGgg2Dou91TLb9u9",
      "uri": "spotify:track:4EoPPRJGgg2Dou91TLb9u9",
      "track_href": "https://api.spotify.com/v1/tracks/4EoPPRJGgg2Dou91TLb9u9",
      "analysis_url": "https://api.spotify.com/v1/audio-analysis/4EoPPRJGgg2Dou91TLb9u9",
      "duration_ms": 197813,
      "time_signature": 1
    },
    {
      "danceability": 0.838,
      "energy": 0.942,
      "key": 5,
      "loudness": -2.353,
      "mode": 1,
      "speechiness": 0.395,
      "acousticness": 0.0718,
      "instrumentalness": 0,
      "liveness": 0.142,
      "valence": 0.961,
      "tempo": 79.935,
      "type": "audio_features",
      "id": "7pWcjb71SqY2256QasmAhJ",
      "uri": "spotify:track:7pWcjb71SqY2256QasmAhJ",
      "track_href": "https://api.spotify.com/v1/tracks/7pWcjb71SqY2256QasmAhJ",
      "analysis_url": "https://api.spotify.com/v1/audio-analysis/7pWcjb71SqY2256QasmAhJ",
      "duration_ms": 270333,
      "time_signature": 4
    },
    {
      "danceability": 0.857,
      "energy": 0.601,
      "key": 2,
      "loudness": -5.837,
      "mode": 1,
      "speechiness": 0.0782,
      "acousticness": 0.00103,
      "instrumentalness": 1.58e-05,
      "liveness": 0.149,
      "valence": 0.279,
      "tempo": 147.076,
      "type": "audio_features",
      "id": "6vbafkvao6NErZDTjh2sYC",
      "uri": "spotify:track:6vbafkvao6NErZDTjh2sYC",
      "track_href": "https://api.spotify.com/v1/tracks/6vbafkvao6NErZDTjh2sYC",
      "analysis_url": "https://api.spotify.com/v1/audio-analysis/6vbafkvao6NErZDTjh2sYC",
      "duration_ms": 218521,
      "time_signature": 4
    },
    {
      "danceability": 0.845,
      "energy": 0.735,
      "key": 0,
      "loudness": -6.077,
      "mode": 1,
      "speechiness": 0.302,
      "acousticness": 0.135,
      "instrumentalness": 0,
      "liveness": 0.147,
      "valence": 0.45,
      "tempo": 129.993,
      "type": "audio_features",
      "id": "0foRpYmPs9PHIAMyXa5bTc",
      "uri": "spotify:track:0foRpYmPs9PHIAMyXa5bTc",
      "track_href": "https://api.spotify.com/v1/tracks/0foRpYmPs9PHIAMyXa5bTc",
      "analysis_url": "https://api.spotify.com/v1/audio-analysis/0foRpYmPs9PHIAMyXa5bTc",
      "duration_ms": 212120,
      "time_signature": 4
    },
    {
      "danceability": 0.765,
      "energy": 0.762,
      "key": 5,
      "loudness": -6.913,
      "mode": 0,
      "speechiness": 0.0478,
      "acousticness": 0.0664,
      "instrumentalness": 0.00287,
      "liveness": 0.11,
      "valence": 0.171,
      "tempo": 120.039,
      "type": "audio_features",
      "id": "6RjB6QyoS0qNRuz1fTdkdy",
      "uri": "spotify:track:6RjB6QyoS0qNRuz1fTdkdy",
      "track_href": "https://api.spotify.com/v1/tracks/6RjB6QyoS0qNRuz1fTdkdy",
      "analysis_url": "https://api.spotify.com/v1/audio-analysis/6RjB6QyoS0qNRuz1fTdkdy",
      "duration_ms": 233968,
      "time_signature": 4
    },
    {
      "danceability": 0.458,
      "energy": 0.747,
      "key": 7,
      "loudness": -4.92,
      "mode": 1,
      "speechiness": 0.039,
      "acousticness": 0.00329,
      "instrumentalness": 5.34e-06,
      "liveness": 0.0817,
      "valence": 0.493,
      "tempo": 104.913,
      "type": "audio_features",
      "id": "3ydXDfJ7hRPAKePR1l0IGZ",
      "uri": "spotify:track:3ydXDfJ7hRPAKePR1l0IGZ",
      "track_href": "https://api.spotify.com/v1/tracks/3ydXDfJ7hRPAKePR1l0IGZ",
      "analysis_url": "https://api.spotify.com/v1/audio-analysis/3ydXDfJ7hRPAKePR1l0IGZ",
      "duration_ms": 269053,
      "time_signature": 4
    },
    {
      "danceability": 0.58,
      "energy": 0.87,
      "key": 10,
      "loudness": -3.385,
      "mode": 1,
      "speechiness": 0.0573,
      "acousticness": 0.0572,
      "instrumentalness": 0.00316,
      "liveness": 0.377,
      "valence": 0.488,
      "tempo": 122.01,
      "type": "audio_features",
      "id": "66r4LELfgqRJDPJ2CdIBZM",
      "uri": "spotify:track:66r4LELfgqRJDPJ2CdIBZM",
      "track_href": "https://api.spotify.com/v1/tracks/66r4LELfgqRJDPJ2CdIBZM",
      "analysis_url": "https://api.spotify.com/v1/audio-analysis/66r4LELfgqRJDPJ2CdIBZM",
      "duration_ms": 246885,
      "time_signature": 4
    },
    {
      "danceability": 0.676,
      "energy": 0.709,
      "key": 0,
      "loudness": -3.563,
      "mode": 0,
      "speechiness": 0.0826,
      "acousticness": 0.107,
      "instrumentalness": 3.28e-06,
      "liveness": 0.0912,
      "valence": 0.275,
      "tempo": 141.986,
      "type": "audio_features",
      "id": "6eEZH8Y3lgmILNqt6SP1Xn",
      "uri": "spotify:track:6eEZH8Y3lgmILNqt6SP1Xn",
      "track_href": "https://api.spotify.com/v1/tracks/6eEZH8Y3lgmILNqt6SP1Xn",
      "analysis_url": "https://api.spotify.com/v1/audio-analysis/6eEZH8Y3lgmILNqt6SP1Xn",
      "duration_ms": 201127,
      "time_signature": 4
    },
    {
      "danceability": 0.83,
      "energy": 0.616,
      "key": 4,
      "loudness": -7.383,
      "mode": 0,
      "speechiness": 0.0499,
      "acousticness": 0.243,
      "instrumentalness": 0,
      "liveness": 0.0477,
      "valence": 0.386,
      "tempo": 123.965,
      "type": "audio_features",
      "id": "2KqyIbbCPKhNfqqzUVq9H9",
      "uri": "spotify:track:2KqyIbbCPKhNfqqzUVq9H9",
      "track_href": "https://api.spotify.com/v1/tracks/2KqyIbbCPKhNfqqzUVq9H9",
      "analysis_url": "https://api.spotify.com/v1/audio-analysis/2KqyIbbCPKhNfqqzUVq9H9",
      "duration_ms": 218600,
      "time_signature": 4
    },
    {
      "danceability": 0.871,
      "energy": 0.883,
      "key": 11,
      "loudness": -5.075,
      "mode": 0,
      "speechiness": 0.105,
      "acousticness": 0.0155,
      "instrumentalness": 0,
      "liveness": 0.14,
      "valence": 0.581,
      "tempo": 125.037,
      "type": "audio_features",
      "id": "43l58ibG1ezgEbFZQUHr7y",
      "uri": "spotify:track:43l58ibG1ezgEbFZQUHr7y",
      "track_href": "https://api.spotify.com/v1/tracks/43l58ibG1ezgEbFZQUHr7y",
      "analysis_url": "https://api.spotify.com/v1/audio-analysis/43l58ibG1ezgEbFZQUHr7y",
      "duration_ms": 231507,
      "time_signature": 4
    },
    {
      "danceability": 0.536,
      "energy": 0.922,
      "key": 2,
      "loudness": -6.247,
      "mode": 1,
      "speechiness": 0.0667,
      "acousticness": 0.0406,
      "instrumentalness": 8.92e-05,
      "liveness": 0.214,
      "valence": 0.353,
      "tempo": 121.977,
      "type": "audio_features",
      "id": "2e3KUBfcAwAyQtgbeUBKob",
      "uri": "spotify:track:2e3KUBfcAwAyQtgbeUBKob",
      "track_href": "https://api.spotify.com/v1/tracks/2e3KUBfcAwAyQtgbeUBKob",
      "analysis_url": "https://api.spotify.com/v1/audio-analysis/2e3KUBfcAwAyQtgbeUBKob",
      "duration_ms": 238893,
      "time_signature": 4
    },
    {
      "danceability": 0.699,
      "energy": 0.675,
      "key": 9,
      "loudness": -5.383,
      "mode": 1,
      "speechiness": 0.387,
      "acousticness": 0.0654,
      "instrumentalness": 0,
      "liveness": 0.143,
      "valence": 0.442,
      "tempo": 105.151,
      "type": "audio_features",
      "id": "4MfOIakexlZ7kIvMQOlCwm",
      "uri": "spotify:track:4MfOIakexlZ7kIvMQOlCwm",
      "track_href": "https://api.spotify.com/v1/tracks/4MfOIakexlZ7kIvMQOlCwm",
      "analysis_url": "https://api.spotify.com/v1/audio-analysis/4MfOIakexlZ7kIvMQOlCwm",
      "duration_ms": 217200,
      "time_signature": 4
    },
    {
      "danceability": 0.347,
      "energy": 0.537,
      "key": 7,
      "loudness": -8.29,
      "mode": 0,
      "speechiness": 0.0562,
      "acousticness": 0.367,
      "instrumentalness": 8.71e-05,
      "liveness": 0.709,
      "valence": 0.39,
      "tempo": 166.553,
      "type": "audio_features",
      "id": "7o9ZrcvgUx1mN38Mi4UVhg",
      "uri": "spotify:track:7o9ZrcvgUx1mN38Mi4UVhg",
      "track_href": "https://api.spotify.com/v1/tracks/7o9ZrcvgUx1mN38Mi4UVhg",
      "analysis_url": "https://api.spotify.com/v1/audio-analysis/7o9ZrcvgUx1mN38Mi4UVhg",
      "duration_ms": 310550,
      "time_signature": 4
    },
    {
      "danceability": 0.296,
      "energy": 0.651,
      "key": 2,
      "loudness": -8.584,
      "mode": 1,
      "speechiness": 0.0315,
      "acousticness": 0.0192,
      "instrumentalness": 0.00231,
      "liveness": 0.08,
      "valence": 0.165,
      "tempo": 108.008,
      "type": "audio_features",
      "id": "1TOAu74vVkdh6p50gGFLEq",
      "uri": "spotify:track:1TOAu74vVkdh6p50gGFLEq",
      "track_href": "https://api.spotify.com/v1/tracks/1TOAu74vVkdh6p50gGFLEq",
      "analysis_url": "https://api.spotify.com/v1/audio-analysis/1TOAu74vVkdh6p50gGFLEq",
      "duration_ms": 326480,
      "time_signature": 4
    },
    {
      "danceability": 0.197,
      "energy": 0.849,
      "key": 2,
      "loudness": -5.268,
      "mode": 1,
      "speechiness": 0.0644,
      "acousticness": 0.195,
      "instrumentalness": 0.00778,
      "liveness": 0.97,
      "valence": 0.321,
      "tempo": 139.039,
      "type": "audio_features",
      "id": "3DptyU1jwV6Hb3bxX4e9eZ",
      "uri": "spotify:track:3DptyU1jwV6Hb3bxX4e9eZ",
      "track_href": "https://api.spotify.com/v1/tracks/3DptyU1jwV6Hb3bxX4e9eZ",
      "analysis_url": "https://api.spotify.com/v1/audio-analysis/3DptyU1jwV6Hb3bxX4e9eZ",
      "duration_ms": 278293,
      "time_signature": 4
    },
    {
      "danceability": 0.682,
      "energy": 0.849,
      "key": 4,
      "loudness": -4.148,
      "mode": 1,
      "speechiness": 0.0312,
      "acousticness": 0.00505,
      "instrumentalness": 8.65e-05,
      "liveness": 0.371,
      "valence": 0.564,
      "tempo": 111.044,
      "type": "audio_features",
      "id": "5JkCyeCL0S3UqzlibpeDdb",
      "uri": "spotify:track:5JkCyeCL0S3UqzlibpeDdb",
      "track_href": "https://api.spotify.com/v1/tracks/5JkCyeCL0S3UqzlibpeDdb",
      "analysis_url": "https://api.spotify.com/v1/audio-analysis/5JkCyeCL0S3UqzlibpeDdb",
      "duration_ms": 218147,
      "time_signature": 4
    },
    {
      "danceability": 0.841,
      "energy": 0.622,
      "key": 6,
      "loudness": -8.129,
      "mode": 0,
      "speechiness": 0.0388,
      "acousticness": 0.411,
      "instrumentalness": 2.94e-05,
      "liveness": 0.208,
      "valence": 0.834,
      "tempo": 130.083,
      "type": "audio_features",
      "id": "5Cgdd7ieR7DvInsOm9f9Ce",
      "uri": "spotify:track:5Cgdd7ieR7DvInsOm9f9Ce",
      "track_href": "https://api.spotify.com/v1/tracks/5Cgdd7ieR7DvInsOm9f9Ce",
      "analysis_url": "https://api.spotify.com/v1/audio-analysis/5Cgdd7ieR7DvInsOm9f9Ce",
      "duration_ms": 213621,
      "time_signature": 4
    },
    {
      "danceability": 0.543,
      "energy": 0.797,
      "key": 1,
      "loudness": -5.296,
      "mode": 0,
      "speechiness": 0.203,
      "acousticness": 0.00329,
      "instrumentalness": 1.67e-06,
      "liveness": 0.0567,
      "valence": 0.601,
      "tempo": 145.956,
      "type": "audio_features",
      "id": "2dPe9cYwR1oWclYqs8fIlY",
      "uri": "spotify:track:2dPe9cYwR1oWclYqs8fIlY",
      "track_href": "https://api.spotify.com/v1/tracks/2dPe9cYwR1oWclYqs8fIlY",
      "analysis_url": "https://api.spotify.com/v1/audio-analysis/2dPe9cYwR1oWclYqs8fIlY",
      "duration_ms": 190325,
      "time_signature": 4
    },
    {
      "danceability": 0.682,
      "energy": 0.646,
      "key": 11,
      "loudness": -5.509,
      "mode": 1,
      "speechiness": 0.0839,
      "acousticness": 0.376,
      "instrumentalness": 0,
      "liveness": 0.0705,
      "valence": 0.253,
      "tempo": 128.279,
      "type": "audio_features",
      "id": "00zqTWtvCWvDtAqoLRl6Sy",
      "uri": "spotify:track:00zqTWtvCWvDtAqoLRl6Sy",
      "track_href": "https://api.spotify.com/v1/tracks/00zqTWtvCWvDtAqoLRl6Sy",
      "analysis_url": "https://api.spotify.com/v1/audio-analysis/00zqTWtvCWvDtAqoLRl6Sy",
      "duration_ms": 236213,
      "time_signature": 4
    },
    {
      "danceability": 0.545,
      "energy": 0.675,
      "key": 6,
      "loudness": -6.474,
      "mode": 1,
      "speechiness": 0.0279,
      "acousticness": 0.00617,
      "instrumentalness": 0.00197,
      "liveness": 0.209,
      "valence": 0.162,
      "tempo": 124.97,
      "type": "audio_features",
      "id": "0FDzzruyVECATHXKHFs9eJ",
      "uri": "spotify:track:0FDzzruyVECATHXKHFs9eJ",
      "track_href": "https://api.spotify.com/v1/tracks/0FDzzruyVECATHXKHFs9eJ",
      "analysis_url": "https://api.spotify.com/v1/audio-analysis/0FDzzruyVECATHXKHFs9eJ",
      "duration_ms": 267867,
      "time_signature": 4
    },
    {
      "danceability": 0.59,
      "energy": 0.733,
      "key": 10,
      "loudness": -7.939,
      "mode": 0,
      "speechiness": 0.0392,
      "acousticness": 0.00356,
      "instrumentalness": 0.559,
      "liveness": 0.0372,
      "valence": 0.301,
      "tempo": 99.999,
      "type": "audio_features",
      "id": "21mECqLKwEjbf5aEOvFMqK",
      "uri": "spotify:track:21mECqLKwEjbf5aEOvFMqK",
      "track_href": "https://api.spotify.com/v1/tracks/21mECqLKwEjbf5aEOvFMqK",
      "analysis_url": "https://api.spotify.com/v1/audio-analysis/21mECqLKwEjbf5aEOvFMqK",
      "duration_ms": 196867,
      "time_signature": 4
    },
    {
      "danceability": 0.603,
      "energy": 0.271,
      "key": 5,
      "loudness": -10.083,
      "mode": 1,
      "speechiness": 0.0284,
      "acousticness": 0.679,
      "instrumentalness": 0,
      "liveness": 0.141,
      "valence": 0.405,
      "tempo": 110.89,
      "type": "audio_features",
      "id": "5K09WxKdlkroDyEVyOSySy",
      "uri": "spotify:track:5K09WxKdlkroDyEVyOSySy",
      "track_href": "https://api.spotify.com/v1/tracks/5K09WxKdlkroDyEVyOSySy",
      "analysis_url": "https://api.spotify.com/v1/audio-analysis/5K09WxKdlkroDyEVyOSySy",
      "duration_ms": 165333,
      "time_signature": 3
    },
    {
      "danceability": 0.506,
      "energy": 0.63,
      "key": 11,
      "loudness": -7.161,
      "mode": 0,
      "speechiness": 0.29,
      "acousticness": 0.737,
      "instrumentalness": 0.00309,
      "liveness": 0.105,
      "valence": 0.216,
      "tempo": 169.766,
      "type": "audio_features",
      "id": "6szbPtOFWRjJRPM7BbKXby",
      "uri": "spotify:track:6szbPtOFWRjJRPM7BbKXby",
      "track_href": "https://api.spotify.com/v1/tracks/6szbPtOFWRjJRPM7BbKXby",
      "analysis_url": "https://api.spotify.com/v1/audio-analysis/6szbPtOFWRjJRPM7BbKXby",
      "duration_ms": 103093,
      "time_signature": 4
    },
    {
      "danceability": 0.465,
      "energy": 0.772,
      "key": 6,
      "loudness": -6.281,
      "mode": 0,
      "speechiness": 0.058,
      "acousticness": 0.0185,
      "instrumentalness": 2.43e-06,
      "liveness": 0.0864,
      "valence": 0.741,
      "tempo": 82.376,
      "type": "audio_features",
      "id": "7bLBekAdZXj48UVI0QpJbO",
      "uri": "spotify:track:7bLBekAdZXj48UVI0QpJbO",
      "track_href": "https://api.spotify.com/v1/tracks/7bLBekAdZXj48UVI0QpJbO",
      "analysis_url": "https://api.spotify.com/v1/audio-analysis/7bLBekAdZXj48UVI0QpJbO",
      "duration_ms": 221573,
      "time_signature": 4
    },
    {
      "danceability": 0.601,
      "energy": 0.715,
      "key": 11,
      "loudness": -4.843,
      "mode": 1,
      "speechiness": 0.0362,
      "acousticness": 0.00831,
      "instrumentalness": 0,
      "liveness": 0.47,
      "valence": 0.606,
      "tempo": 94.976,
      "type": "audio_features",
      "id": "43yFiQ18Nhnb2YJwk09f3a",
      "uri": "spotify:track:43yFiQ18Nhnb2YJwk09f3a",
      "track_href": "https://api.spotify.com/v1/tracks/43yFiQ18Nhnb2YJwk09f3a",
      "analysis_url": "https://api.spotify.com/v1/audio-analysis/43yFiQ18Nhnb2YJwk09f3a",
      "duration_ms": 186000,
      "time_signature": 4
    },
    {
      "danceability": 0.78,
      "energy": 0.846,
      "key": 10,
      "loudness": -5.935,
      "mode": 0,
      "speechiness": 0.194,
      "acousticness": 0.171,
      "instrumentalness": 0,
      "liveness": 0.0927,
      "valence": 0.699,
      "tempo": 88.065,
      "type": "audio_features",
      "id": "0BHf5WfJNXGi2Fhj5uCrvz",
      "uri": "spotify:track:0BHf5WfJNXGi2Fhj5uCrvz",
      "track_href": "https://api.spotify.com/v1/tracks/0BHf5WfJNXGi2Fhj5uCrvz",
      "analysis_url": "https://api.spotify.com/v1/audio-analysis/0BHf5WfJNXGi2Fhj5uCrvz",
      "duration_ms": 285507,
      "time_signature": 4
    },
    {
      "danceability": 0.727,
      "energy": 0.588,
      "key": 10,
      "loudness": -10.633,
      "mode": 0,
      "speechiness": 0.0507,
      "acousticness": 0.00273,
      "instrumentalness": 0.0107,
      "liveness": 0.101,
      "valence": 0.533,
      "tempo": 90.003,
      "type": "audio_features",
      "id": "4m4wNBTovgaJiOl5gZkvWS",
      "uri": "spotify:track:4m4wNBTovgaJiOl5gZkvWS",
      "track_href": "https://api.spotify.com/v1/tracks/4m4wNBTovgaJiOl5gZkvWS",
      "analysis_url": "https://api.spotify.com/v1/audio-analysis/4m4wNBTovgaJiOl5gZkvWS",
      "duration_ms": 184640,
      "time_signature": 4
    },
    {
      "danceability": 0.695,
      "energy": 0.934,
      "key": 0,
      "loudness": -5.377,
      "mode": 0,
      "speechiness": 0.377,
      "acousticness": 0.0351,
      "instrumentalness": 4.65e-06,
      "liveness": 0.215,
      "valence": 0.28,
      "tempo": 146.066,
      "type": "audio_features",
      "id": "6q2vmuMPbLEK3AUfMG608M",
      "uri": "spotify:track:6q2vmuMPbLEK3AUfMG608M",
      "track_href": "https://api.spotify.com/v1/tracks/6q2vmuMPbLEK3AUfMG608M",
      "analysis_url": "https://api.spotify.com/v1/audio-analysis/6q2vmuMPbLEK3AUfMG608M",
      "duration_ms": 230560,
      "time_signature": 4
    },
    {
      "danceability": 0.914,
      "energy": 0.772,
      "key": 11,
      "loudness": -3.919,
      "mode": 0,
      "speechiness": 0.249,
      "acousticness": 0.182,
      "instrumentalness": 0,
      "liveness": 0.201,
      "valence": 0.506,
      "tempo": 119.03,
      "type": "audio_features",
      "id": "3dkyEOVeime8KWl1WicuPM",
      "uri": "spotify:track:3dkyEOVeime8KWl1WicuPM",
      "track_href": "https://api.spotify.com/v1/tracks/3dkyEOVeime8KWl1WicuPM",
      "analysis_url": "https://api.spotify.com/v1/audio-analysis/3dkyEOVeime8KWl1WicuPM",
      "duration_ms": 171003,
      "time_signature": 4
    },
    {
      "danceability": 0.526,
      "energy": 0.84,
      "key": 11,
      "loudness": -8.022,
      "mode": 0,
      "speechiness": 0.0398,
      "acousticness": 0.00114,
      "instrumentalness": 0.423,
      "liveness": 0.237,
      "valence": 0.478,
      "tempo": 123.173,
      "type": "audio_features",
      "id": "2fea1IQDXMABCGce4H5dzZ",
      "uri": "spotify:track:2fea1IQDXMABCGce4H5dzZ",
      "track_href": "https://api.spotify.com/v1/tracks/2fea1IQDXMABCGce4H5dzZ",
      "analysis_url": "https://api.spotify.com/v1/audio-analysis/2fea1IQDXMABCGce4H5dzZ",
      "duration_ms": 266440,
      "time_signature": 4
    },
    {
      "danceability": 0.629,
      "energy": 0.882,
      "key": 8,
      "loudness": -6.061,
      "mode": 0,
      "speechiness": 0.113,
      "acousticness": 0.188,
      "instrumentalness": 0.0128,
      "liveness": 0.573,
      "valence": 0.354,
      "tempo": 120.026,
      "type": "audio_features",
      "id": "0tEjjVdIQM2i3z3Cmlt0er",
      "uri": "spotify:track:0tEjjVdIQM2i3z3Cmlt0er",
      "track_href": "https://api.spotify.com/v1/tracks/0tEjjVdIQM2i3z3Cmlt0er",
      "analysis_url": "https://api.spotify.com/v1/audio-analysis/0tEjjVdIQM2i3z3Cmlt0er",
      "duration_ms": 199000,
      "time_signature": 4
    },
    {
      "danceability": 0.376,
      "energy": 0.795,
      "key": 4,
      "loudness": -6.067,
      "mode": 1,
      "speechiness": 0.0454,
      "acousticness": 0.00294,
      "instrumentalness": 6.56e-06,
      "liveness": 0.0562,
      "valence": 0.218,
      "tempo": 149.995,
      "type": "audio_features",
      "id": "0au5u99zsQ6yunHfywDX8a",
      "uri": "spotify:track:0au5u99zsQ6yunHfywDX8a",
      "track_href": "https://api.spotify.com/v1/tracks/0au5u99zsQ6yunHfywDX8a",
      "analysis_url": "https://api.spotify.com/v1/audio-analysis/0au5u99zsQ6yunHfywDX8a",
      "duration_ms": 315307,
      "time_signature": 4
    },
    {
      "danceability": 0.586,
      "energy": 0.538,
      "key": 1,
      "loudness": -8.297,
      "mode": 1,
      "speechiness": 0.26,
      "acousticness": 0.301,
      "instrumentalness": 0,
      "liveness": 0.35,
      "valence": 0.258,
      "tempo": 70.271,
      "type": "audio_features",
      "id": "5bmrx5bUNmtliMz9mVcQl8",
      "uri": "spotify:track:5bmrx5bUNmtliMz9mVcQl8",
      "track_href": "https://api.spotify.com/v1/tracks/5bmrx5bUNmtliMz9mVcQl8",
      "analysis_url": "https://api.spotify.com/v1/audio-analysis/5bmrx5bUNmtliMz9mVcQl8",
      "duration_ms": 254713,
      "time_signature": 4
    },
    {
      "danceability": 0.729,
      "energy": 0.756,
      "key": 4,
      "loudness": -4.424,
      "mode": 1,
      "speechiness": 0.0715,
      "acousticness": 0.161,
      "instrumentalness": 0,
      "liveness": 0.0591,
      "valence": 0.693,
      "tempo": 150.086,
      "type": "audio_features",
      "id": "2wGmhCboanR7HOK0IKbuDH",
      "uri": "spotify:track:2wGmhCboanR7HOK0IKbuDH",
      "track_href": "https://api.spotify.com/v1/tracks/2wGmhCboanR7HOK0IKbuDH",
      "analysis_url": "https://api.spotify.com/v1/audio-analysis/2wGmhCboanR7HOK0IKbuDH",
      "duration_ms": 135307,
      "time_signature": 4
    },
    {
      "danceability": 0.688,
      "energy": 0.555,
      "key": 10,
      "loudness": -5.418,
      "mode": 0,
      "speechiness": 0.0323,
      "acousticness": 0.0114,
      "instrumentalness": 0.315,
      "liveness": 0.102,
      "valence": 0.27,
      "tempo": 99.973,
      "type": "audio_features",
      "id": "26aVIjuka4gVm6EHy0NJrj",
      "uri": "spotify:track:26aVIjuka4gVm6EHy0NJrj",
      "track_href": "https://api.spotify.com/v1/tracks/26aVIjuka4gVm6EHy0NJrj",
      "analysis_url": "https://api.spotify.com/v1/audio-analysis/26aVIjuka4gVm6EHy0NJrj",
      "duration_ms": 202533,
      "time_signature": 4
    },
    {
      "danceability": 0.617,
      "energy": 0.731,
      "key": 3,
      "loudness": -5.917,
      "mode": 0,
      "speechiness": 0.0732,
      "acousticness": 0.445,
      "instrumentalness": 0,
      "liveness": 0.175,
      "valence": 0.488,
      "tempo": 131.966,
      "type": "audio_features",
      "id": "2JbYoUC409rNEm1sn8fZiP",
      "uri": "spotify:track:2JbYoUC409rNEm1sn8fZiP",
      "track_href": "https://api.spotify.com/v1/tracks/2JbYoUC409rNEm1sn8fZiP",
      "analysis_url": "https://api.spotify.com/v1/audio-analysis/2JbYoUC409rNEm1sn8fZiP",
      "duration_ms": 239960,
      "time_signature": 4
    },
    {
      "danceability": 0.66,
      "energy": 0.695,
      "key": 9,
      "loudness": -6.896,
      "mode": 0,
      "speechiness": 0.029,
      "acousticness": 0.0466,
      "instrumentalness": 0.145,
      "liveness": 0.0854,
      "valence": 0.506,
      "tempo": 129.972,
      "type": "audio_features",
      "id": "3Vn9oCZbdI1EMO7jxdz2Rc",
      "uri": "spotify:track:3Vn9oCZbdI1EMO7jxdz2Rc",
      "track_href": "https://api.spotify.com/v1/tracks/3Vn9oCZbdI1EMO7jxdz2Rc",
      "analysis_url": "https://api.spotify.com/v1/audio-analysis/3Vn9oCZbdI1EMO7jxdz2Rc",
      "duration_ms": 382387,
      "time_signature": 4
    },
    {
      "danceability": 0.569,
      "energy": 0.316,
      "key": 11,
      "loudness": -9.762,
      "mode": 0,
      "speechiness": 0.0475,
      "acousticness": 0.871,
      "instrumentalness": 0,
      "liveness": 0.115,
      "valence": 0.235,
      "tempo": 118.297,
      "type": "audio_features",
      "id": "5iJS04ZXjMkQZ5nS0PsIeY",
      "uri": "spotify:track:5iJS04ZXjMkQZ5nS0PsIeY",
      "track_href": "https://api.spotify.com/v1/tracks/5iJS04ZXjMkQZ5nS0PsIeY",
      "analysis_url": "https://api.spotify.com/v1/audio-analysis/5iJS04ZXjMkQZ5nS0PsIeY",
      "duration_ms": 265456,
      "time_signature": 4
    },
    {
      "danceability": 0.755,
      "energy": 0.751,
      "key": 8,
      "loudness": -4.034,
      "mode": 1,
      "speechiness": 0.0748,
      "acousticness": 0.0635,
      "instrumentalness": 0,
      "liveness": 0.0812,
      "valence": 0.491,
      "tempo": 102.002,
      "type": "audio_features",
      "id": "0V9cosR5jWa4fr2koARmhD",
      "uri": "spotify:track:0V9cosR5jWa4fr2koARmhD",
      "track_href": "https://api.spotify.com/v1/tracks/0V9cosR5jWa4fr2koARmhD",
      "analysis_url": "https://api.spotify.com/v1/audio-analysis/0V9cosR5jWa4fr2koARmhD",
      "duration_ms": 183587,
      "time_signature": 4
    }
  ]
}
