{
  "audio_features": [
    null,
    {
      "danceability": 0.363,
      "energy": 0.971,
      "key": 5,
      "loudness": -2.974,
      "mode": 0,
      "speechiness": 0.0776,
      "acousticness": 7.1e-06,
      "instrumentalness": 0.00358,
      "liveness": 0.0797,
      "valence": 0.347,
      "tempo": 146.018,
      "type": "audio_features",
      "id": "6EF0xhfKtQNqUPz2mnE5BD",
      "uri": "spotify:track:6EF0xhfKtQNqUPz2mnE5BD",
      "track_href": "https://api.spotify.com/v1/tracks/6EF0xhfKtQNqUPz2mnE5BD",
      "analysis_url": "https://api.spotify.com/v1/audio-analysis/6EF0xhfKtQNqUPz2mnE5BD",
      "duration_ms": 299787,
      "time_signature": 4
    },
    {
      "danceability": 0.33,
      "energy": 0.941,
      "key": 9,
      "loudness": -2.83,
      "mode": 0,
      "speechiness": 0.0909,
      "acousticness": 0.000133,
      "instrumentalness": 2.68e-06,
      "liveness": 0.0647,
      "valence": 0.159,
      "tempo": 160.209,
      "type": "audio_features",
      "id": "2up4oiwaVjL7nDDWjCSp6s",
      "uri": "spotify:track:2up4oiwaVjL7nDDWjCSp6s",
      "track_href": "https://api.spotify.com/v1/tracks/2up4oiwaVjL7nDDWjCSp6s",
      "analysis_url": "https://api.spotify.com/v1/audio-analysis/2up4oiwaVjL7nDDWjCSp6s",
      "duration_ms": 210227,
      "time_signature": 4
    },
    {
      "danceability": 0.805,
      "energy": 0.654,
      "key": 7,
      "loudness": -7.072,
      "mode": 1,
      "speechiness": 0.056,
      "acousticness": 0.00271,
      "instrumentalness": 0.00993,
      "liveness": 0.141,
      "valence": 0.842,
      "tempo": 89.738,
      "type": "audio_features",
      "id": "3Ji3MhxkAHYs8Byc3O1Jgk",
      "uri": "spotify:track:3Ji3MhxkAHYs8Byc3O1Jgk",
      "track_href": "https://api.spotify.com/v1/tracks/3Ji3MhxkAHYs8Byc3O1Jgk",
      "analysis_url": "https://api.spotify.com/v1/audio-analysis/3Ji3MhxkAHYs8Byc3O1Jgk",
      "duration_ms": 252293,
      "time_signature": 4
    },
    {
      "danceability": 0.634,
      "energy": 0.649,
      "key": 6,
      "loudness": -7.505,
      "mode": 0,
      "speechiness": 0.0486,
      "acousticness": 0.0315,
      "instrumentalness": 0,
      "liveness": 0.482,
      "valence": 0.509,
      "tempo": 90.482,
      "type": "audio_features",
      "id": "0ua0Go4NN4Td7l0Zre6Ce3",
      "uri": "spotify:track:0ua0Go4NN4Td7l0Zre6Ce3",
      "track_href": "https://api.spotify.com/v1/tracks/0ua0Go4NN4Td7l0Zre6Ce3",
      "analysis_url": "https://api.spotify.com/v1/audio-analysis/0ua0Go4NN4Td7l0Zre6Ce3",
      "duration_ms": 237507,
      "time_signature": 4
    },
    {
      "danceability": 0.718,
      "energy": 0.86,
      "key": 5,
      "loudness": -4.162,
      "mode": 1,
      "speechiness": 0.0409,
      "acousticness": 0.252,
      "instrumentalness": 0,
      "liveness": 0.0703,
      "valence": 0.883,
      "tempo": 93.022,
      "type": "audio_features",
      "id": "02H8JYd2hItFqfppgu5efp",
      "uri": "spotify:track:02H8JYd2hItFqfppgu5efp",
      "track_href": "https://api.spotify.com/v1/tracks/02H8JYd2hItFqfppgu5efp",
      "analysis_url": "https://api.spotify.com/v1/audio-analysis/02H8JYd2hItFqfppgu5efp",
      "duration_ms": 170918,
      "time_signature": 4
    },
    {
      "danceability": 0.525,
      "energy": 0.8,
      "key": 11,
      "loudness": -11.484,
      "mode": 1,
      "speechiness": 0.122,
      "acousticness": 0.000478,
      "instrumentalness": 0.429,
      "liveness": 0.319,
      "valence": 0.528,
      "tempo": 80.032,
      "type": "audio_features",
      "id": "0FNjwjqMA5YvlTWsOG8qUO",
      "uri": "spotify:track:0FNjwjqMA5YvlTWsOG8qUO",
      "track_href": "https://api.spotify.com/v1/tracks/0FNjwjqMA5YvlTWsOG8qUO",
      "analysis_url": "https://api.spotify.com/v1/audio-analysis/0FNjwjqMA5YvlTWsOG8qUO",
      "duration_ms": 200015,
      "time_signature": 4
    },
    {
      "danceability": 0.605,
      "energy": 0.615,
      "key": 8,
      "loudness": -5.617,
      "mode": 1,
      "speechiness": 0.0474,
      "acousticness": 0.479,
      "instrumentalness": 0,
      "liveness": 0.137,
      "valence": 0.841,
      "tempo": 172.211,
      "type": "audio_features",
      "id": "63OB8oKmBUUYiRtrRtFCvX",
      "uri": "spotify:track:63OB8oKmBUUYiRtrRtFCvX",
      "track_href": "https://api.spotify.com/v1/tracks/63OB8oKmBUUYiRtrRtFCvX",
      "analysis_url": "https://api.spotify.com/v1/audio-analysis/63OB8oKmBUUYiRtrRtFCvX",
      "duration_ms": 213787,
      "time_signature": 4
    },
    {
      "danceability": 0.822,
      "energy": 0.276,
      "key": 1,
      "loudness": -10.556,
      "mode": 1,
      "speechiness": 0.124,
      "acousticness": 0.0395,
      "instrumentalness": 0.0233,
      "liveness": 0.11,
      "valence": 0.0569,
      "tempo": 144.897,
      "type": "audio_features",
      "id": "54i1CQFlT3LeGdIVctDQp1",
      "uri": "spotify:track:54i1CQFlT3LeGdIVctDQp1",
      "track_href": "https://api.spotify.com/v1/tracks/54i1CQFlT3LeGdIVctDQp1",
      "analysis_url": "https://api.spotify.com/v1/audio-analysis/54i1CQFlT3LeGdIVctDQp1",
      "duration_ms": 213427,
      "time_signature": 4
    },
    {
      "danceability": 0,
      "energy": 0.0721,
      "key": 2,
      "loudness": -22.48,
      "mode": 1,
      "speechiness": 0,
      "acousticness": 0.618,
      "instrumentalness": 0.694,
      "liveness": 0,
      "valence": 0,
      "tempo": 0,
      "type": "audio_features",
      "id": "4Fz1WWr5o0OrlIcZxcyZtK",
      "uri": "spotify:track:4Fz1WWr5o0OrlIcZxcyZtK",
      "track_href": "https://api.spotify.com/v1/tracks/4Fz1WWr5o0OrlIcZxcyZtK",
      "analysis_url": "https://api.spotify.com/v1/audio-analysis/4Fz1WWr5o0OrlIcZxcyZtK",
      "duration_ms": 7229,
      "time_signature": 0
    },
    {
      "danceability": 0.623,
      "energy": 0.896,
      "key": 0,
      "loudness": -4.719,
      "mode": 1,
      "speechiness": 0.247,
      "acousticness": 0.035,
      "instrumentalness": 0,
      "liveness": 0.0941,
      "valence": 0.613,
      "tempo": 95.158,
      "type": "audio_features",
      "id": "4cNhx6OO1XpvwT6xZnb83B",
      "uri": "spotify:track:4cNhx6OO1XpvwT6xZnb83B",
      "track_href": "https://api.spotify.com/v1/tracks/4cNhx6OO1XpvwT6xZnb83B",
      "analysis_url": "https://api.spotify.com/v1/audio-analysis/4cNhx6OO1XpvwT6xZnb83B",
      "duration_ms": 300933,
      "time_signature": 4
    },
    {
      "danceability": 0.831,
      "energy": 0.555,
      "key": 9,
      "loudness": -7.634,
      "mode": 0,
      "speechiness": 0.0364,
      "acousticness": 0.0238,
      "instrumentalness": 0.0253,
      "liveness": 0.0869,
      "valence": 0.8,
      "tempo": 94.985,
      "type": "audio_features",
      "id": "4exuQlaeNkyayLXTgjeNoC",
      "uri": "spotify:track:4exuQlaeNkyayLXTgjeNoC",
      "track_href": "https://api.spotify.com/v1/tracks/4exuQlaeNkyayLXTgjeNoC",
      "analysis_url": "https://api.spotify.com/v1/audio-analysis/4exuQlaeNkyayLXTgjeNoC",
      "duration_ms": 203333,
      "time_signature": 4
    },
    {
      "danceability": 0.857,
      "energy": 0.548,
      "key": 9,
      "loudness": -9.545,
      "mode": 1,
      "speechiness": 0.261,
      "acousticness": 0.00134,
      "instrumentalness": 0.109,
      "liveness": 0.113,
      "valence": 0.111,
      "tempo": 120.387,
      "type": "audio_features",
      "id": "0gqF7R97DiR2IkvhjWWUcf",
      "uri": "spotify:track:0gqF7R97DiR2IkvhjWWUcf",
      "track_href": "https://api.spotify.com/v1/tracks/0gqF7R97DiR2IkvhjWWUcf",
      "analysis_url": "https://api.spotify.com/v1/audio-analysis/0gqF7R97DiR2IkvhjWWUcf",
      "duration_ms": 227318,
      "time_signature": 4
    },
    {
      "danceability": 0.753,
      "energy": 0.541,
      "key": 7,
      "loudness": -8.177,
      "mode": 1,
      "speechiness": 0.0464,
      "acousticness": 0.475,
      "instrumentalness": 1.67e-05,
      "liveness": 0.109,
      "valence": 0.547,
      "tempo": 139.96,
      "type": "audio_features",
      "id": "2Jy3mCSPdtwDxRr8LgyPol",
      "uri": "spotify:track:2Jy3mCSPdtwDxRr8LgyPol",
      "track_href": "https://api.spotify.com/v1/tracks/2Jy3mCSPdtwDxRr8LgyPol",
      "analysis_url": "https://api.spotify.com/v1/audio-analysis/2Jy3mCSPdtwDxRr8LgyPol",
      "duration_ms": 237133,
      "time_signature": 4
    },
    {
      "danceability": 0.546,
      "energy": 0.425,
      "key": 4,
      "loudness": -13.111,
      "mode": 1,
      "speechiness": 0.0257,
      "acousticness": 0.138,
      "instrumentalness": 9.45e-06,
      "liveness": 0.0615,
      "valence": 0.514,
      "tempo": 83.151,
      "type": "audio_features",
      "id": "4bltr2sgQOeU13onNoHUTc",
      "uri": "spotify:track:4bltr2sgQOeU13onNoHUTc",
      "track_href": "https://api.spotify.com/v1/tracks/4bltr2sgQOeU13onNoHUTc",
      "analysis_url": "https://api.spotify.com/v1/audio-analysis/4bltr2sgQOeU13onNoHUTc",
      "duration_ms": 234467,
      "time_signature": 4
    },
    {
      "danceability": 0.701,
      "energy": 0.542,
      "key": 2,
      "loudness": -7.594,
      "mode": 1,
      "speechiness": 0.556,
      "acousticness": 0.0423,
      "instrumentalness": 0,
      "liveness": 0.0514,
      "valence": 0.4,
      "tempo": 176.537,
      "type": "audio_features",
      "id": "109UvUQIiDun7V97F56UnN",
      "uri": "spotify:track:109UvUQIiDun7V97F56UnN",
      "track_href": "https://api.spotify.com/v1/tracks/109UvUQIiDun7V97F56UnN",
      "analysis_url": "https://api.spotify.com/v1/audio-analysis/109UvUQIiDun7V97F56UnN",
      "duration_ms": 167727,
      "time_signature": 4
    },
    {
      "danceability": 0.509,
      "energy": 0.802,
      "key": 0,
      "loudness": -7.452,
      "mode": 0,
      "speechiness": 0.0477,
      "acousticness": 0.0194,
      "instrumentalness": 0.168,
      "liveness": 0.198,
      "valence": 0.212,
      "tempo": 140.108,
      "type": "audio_features",
      "id": "1SCpAAw3towOivp0UoNiV1",
      "uri": "spotify:track:1SCpAAw3towOivp0UoNiV1",
      "track_href": "https://api.spotify.com/v1/tracks/1SCpAAw3towOivp0UoNiV1",
      "analysis_url": "https://api.spotify.com/v1/audio-analysis/1SCpAAw3towOivp0UoNiV1",
      "duration_ms": 308571,
      "time_signature": 4
    },
    {
      "danceability": 0.758,
      "energy": 0.597,
      "key": 1,
      "loudness": -7.194,
      "mode": 1,
      "speechiness": 0.093,
      "acousticness": 0.117,
      "instrumentalness": 0,
      "liveness": 0.0991,
      "valence": 0.397,
      "tempo": 108.015,
      "type": "audio_features",
      "id": "3SpNcIpA5QvcQ0YIia8Bmx",
      "uri": "spotify:track:3SpNcIpA5QvcQ0YIia8Bmx",
      "track_href": "https://api.spotify.com/v1/tracks/3SpNcIpA5QvcQ0YIia8Bmx",
      "analysis_url": "https://api.spotify.com/v1/audio-analysis/3SpNcIpA5QvcQ0YIia8Bmx",
      "duration_ms": 297267,
      "time_signature": 4
    },
    {
      "danceability": 0.539,
      "energy": 0.877,
      "key": 4,
      "loudness": -4.848,
      "mode": 1,
      "speechiness": 0.0548,
      "acousticness": 0.107,
      "instrumentalness": 0,
      "liveness": 0.0805,
      "valence": 0.906,
      "tempo": 169.986,
      "type": "audio_features",
      "id": "2eBy71gLx049nJ2fsvuQjM",
      "uri": "spotify:track:2eBy71gLx049nJ2fsvuQjM",
      "track_href": "https://api.spotify.com/v1/tracks/2eBy71gLx049nJ2fsvuQjM",
      "analysis_url": "https://api.spotify.com/v1/audio-analysis/2eBy71gLx049nJ2fsvuQjM",
      "duration_ms": 203319,
      "time_signature": 4
    },
    {
      "danceability": 0.789,
      "energy": 0.384,
      "key": 6,
      "loudness": -9.372,
      "mode": 1,
      "speechiness": 0.0476,
      "acousticness": 0.853,
      "instrumentalness": 0.0322,
      "liveness": 0.0622,
      "valence": 0.528,
      "tempo": 78.413,
      "type": "audio_features",
      "id": "5Hw6DiMO1X31YuhSw1dh5r",
      "uri": "spotify:track:5Hw6DiMO1X31YuhSw1dh5r",
      "track_href": "https://api.spotify.com/v1/tracks/5Hw6DiMO1X31YuhSw1dh5r",
      "analysis_url": "https://api.spotify.com/v1/audio-analysis/5Hw6DiMO1X31YuhSw1dh5r",
      "duration_ms": 203333,
      "time_signature": 4
    },
    {
      "danceability": 0.546,
      "energy": 0.98,
      "key": 9,
      "loudness": -3.02,
      "mode": 0,
      "speechiness": 0.0619,
      "acousticness": 0.0154,
      "instrumentalness": 0,
      "liveness": 0.31,
      "valence": 0.478,
      "tempo": 120.037,
      "type": "audio_features",
      "id": "2oNYsdCasRRlz1shXFAz7D",
      "uri": "spotify:track:2oNYsdCasRRlz1shXFAz7D",
      "track_href": "https://api.spotify.com/v1/tracks/2oNYsdCasRRlz1shXFAz7D",
      "analysis_url": "https://api.spotify.com/v1/audio-analysis/2oNYsdCasRRlz1shXFAz7D",
      "duration_ms": 205120,
      "time_signature": 4
    },
    {
      "danceability": 0.61,
      "energy": 0.813,
      "key": 9,
      "loudness": -6.345,
      "mode": 1,
      "speechiness": 0.0458,
      "acousticness": 0.00637,
      "instrumentalness": 0,
      "liveness": 0.35,
      "valence": 0.429,
      "tempo": 130.974,
      "type": "audio_features",
      "id": "7xgGsdFJbQegq1ClBnlKLd",
      "uri": "spotify:track:7xgGsdFJbQegq1ClBnlKLd",
      "track_href": "https://api.spotify.com/v1/tracks/7xgGsdFJbQegq1ClBnlKLd",
      "analysis_url": "https://api.spotify.com/v1/audio-analysis/7xgGsdFJbQegq1ClBnlKLd",
      "duration_ms": 221677,
      "time_signature": 4
    },
    {
      "danceability": 0.575,
      "energy": 0.933,
      "key": 7,
      "loudness": -2.719,
      "mode": 1,
      "speechiness": 0.051,
      "acousticness": 0.00822,
      "instrumentalness": 0,
      "liveness": 0.244,
      "valence": 0.848,
      "tempo": 135.5,
      "type": "audio_features",
      "id": "5PLC7cNlxWIMAZvXrtqsZm",
      "uri": "spotify:track:5PLC7cNlxWIMAZvXrtqsZm",
      "track_href": "https://api.spotify.com/v1/tracks/5PLC7cNlxWIMAZvXrtqsZm",
      "analysis_url": "https://api.spotify.com/v1/audio-analysis/5PLC7cNlxWIMAZvXrtqsZm",
      "duration_ms": 193600,
      "time_signature": 4
    },
    {
      "danceability": 0.506,
      "energy": 0.723,
      "key": 1,
      "loudness": -5.447,
      "mode": 0,
      "speechiness": 0.0798,
      "acousticness": 0.00407,
      "instrumentalness": 0.000184,
      "liveness": 0.422,
      "valence": 0.503,
      "tempo": 135.034,
      "type": "audio_features",
      "id": "33QCNK7RkiNBfIgMSgTeMD",
      "uri": "spotify:track:33QCNK7RkiNBfIgMSgTeMD",
      "track_href": "https://api.spotify.com/v1/tracks/33QCNK7RkiNBfIgMSgTeMD",
      "analysis_url": "https://api.spotify.com/v1/audio-analysis/33QCNK7RkiNBfIgMSgTeMD",
      "duration_ms": 179920,
      "time_signature": 4
    },
    {
      "danceability": 0.501,
      "energy": 0.682,
      "key": 7,
      "loudness": -4.39,
      "mode": 1,
      "speechiness": 0.0315,
      "acousticness": 0.00815,
      "instrumentalness": 0,
      "liveness": 0.305,
      "valence": 0.0693,
      "tempo": 104.819,
      "type": "audio_features",
      "id": "0TXgq7rZxEfjGGpT0leanv",
      "uri": "spotify:track:0TXgq7rZxEfjGGpT0leanv",
      "track_href": "https://api.spotify.com/v1/tracks/0TXgq7rZxEfjGGpT0leanv",
      "analysis_url": "https://api.spotify.com/v1/audio-analysis/0TXgq7rZxEfjGGpT0leanv",
      "duration_ms": 210286,
      "time_signature": 4
    },
    {
      "danceability": 0.541,
      "energy": 0.904,
      "key": 7,
      "loudness": -3.001,
      "mode": 1,
      "speechiness": 0.0435,
      "acousticness": 0.00143,
      "instrumentalness": 0,
      "liveness": 0.193,
      "valence": 0.541,
      "tempo": 98.122,
      "type": "audio_features",
      "id": "5jZ1Z2GFTf2gwmFc3qiUxs",
      "uri": "spotify:track:5jZ1Z2GFTf2gwmFc3qiUxs",
      "track_href": "https://api.spotify.com/v1/tracks/5jZ1Z2GFTf2gwmFc3qiUxs",
      "analysis_url": "https://api.spotify.com/v1/audio-analysis/5jZ1Z2GFTf2gwmFc3qiUxs",
      "duration_ms": 208693,
      "time_signature": 4
    },
    {
      "danceability": 0.807,
      "energy": 0.556,
      "key": 0,
      "loudness": -5.539,
      "mode": 0,
      "speechiness": 0.119,
      "acousticness": 0.157,
      "instrumentalness": 0,
      "liveness": 0.0906,
      "valence": 0.383,
      "tempo": 87.852,
      "type": "audio_features",
      "id": "5243RHbTTd4oci9YjktHBW",
      "uri": "spotify:track:5243RHbTTd4oci9YjktHBW",
      "track_href": "https://api.spotify.com/v1/tracks/5243RHbTTd4oci9YjktHBW",
      "analysis_url": "https://api.spotify.com/v1/audio-analysis/5243RHbTTd4oci9YjktHBW",
      "duration_ms": 163587,
      "time_signature": 4
    },
    {
      "danceability": 0.113,
      "energy": 0.951,
      "key": 0,
      "loudness": -4.743,
      "mode": 0,
      "speechiness": 0.129,
      "acousticness": 0.00176,
      "instrumentalness": 0.00718,
      "liveness": 0.334,
      "valence": 0.139,
      "tempo": 200.024,
      "type": "audio_features",
      "id": "6nnacTL5on2aVsRhVDNUSo",
      "uri": "spotify:track:6nnacTL5on2aVsRhVDNUSo",
      "track_href": "https://api.spotify.com/v1/tracks/6nnacTL5on2aVsRhVDNUSo",
      "analysis_url": "https://api.spotify.com/v1/audio-analysis/6nnacTL5on2aVsRhVDNUSo",
      "duration_ms": 441560,
      "time_signature": 4
    },
    {
      "danceability": 0.638,
      "energy": 0.893,
      "key": 1,
      "loudness": -3.889,
      "mode": 1,
      "speechiness": 0.0461,
      "acousticness": 0.0446,
      "instrumentalness": 1.59e-06,
      "liveness": 0.0847,
      "valence": 0.87,
      "tempo": 92.018,
      "type": "audio_features",
      "id": "3aOnLQ7Q5bUxB8mqYWb7iX",
      "uri": "spotify:track:3aOnLQ7Q5bUxB8mqYWb7iX",
      "track_href": "https://api.spotify.com/v1/tracks/3aOnLQ7Q5bUxB8mqYWb7iX",
      "analysis_url": "https://api.spotify.com/v1/audio-analysis/3aOnLQ7Q5bUxB8mqYWb7iX",
      "duration_ms": 192653,
      "time_signature": 4
    },
    {
      "danceability": 0.9,
      "energy": 0.778,
      "key": 0,
      "loudness": -4.471,
      "mode": 1,
      "speechiness": 0.158,
      "acousticness": 0.0914,
      "instrumentalness": 0,
      "liveness": 0.145,
      "valence": 0.181,
      "tempo": 115.003,
      "type": "audio_features",
      "id": "0DknII9CrtEehLjFpO4c2R",
      "uri": "spotify:track:0DknII9CrtEehLjFpO4c2R",
      "track_href": "https://api.spotify.com/v1/tracks/0DknII9CrtEehLjFpO4c2R",
      "analysis_url": "https://api.spotify.com/v1/audio-analysis/0DknII9CrtEehLjFpO4c2R",
      "duration_ms": 223053,
      "time_signature": 4
    },
    {
      "danceability": 0.773,
      "energy": 0.263,
      "key": 4,
      "loudness": -8.879,
      "mode": 0,
      "speechiness": 0.0574,
      "acousticness": 0.296,
      "instrumentalness": 0.126,
      "liveness": 0.139,
      "valence": 0.518,
      "tempo": 90.687,
      "type": "audio_features",
      "id": "29j4EY2vlbQH1qzzi6awX9",
      "uri": "spotify:track:29j4EY2vlbQH1qzzi6awX9",
      "track_href": "https://api.spotify.com/v1/tracks/29j4EY2vlbQH1qzzi6awX9",
      "analysis_url": "https://api.spotify.com/v1/audio-analysis/29j4EY2vlbQH1qzzi6awX9",
      "duration_ms": 266187,
      "time_signature": 4
    },
    {
      "danceability": 0.371,
      "energy": 0.377,
      "key": 4,
      "loudness": -9.979,
      "mode": 1,
      "speechiness": 0.0527,
      "acousticness": 0.694,
      "instrumentalness": 0.5,
      "liveness": 0.0986,
      "valence": 0.111,
      "tempo": 126.745,
      "type": "audio_features",
      "id": "3vJJlApCOjUD0NBxrMuOJp",
      "uri": "spotify:track:3vJJlApCOjUD0NBxrMuOJp",
      "track_href": "https://api.spotify.com/v1/tracks/3vJJlApCOjUD0NBxrMuOJp",
      "analysis_url": "https://api.spotify.com/v1/audio-analysis/3vJJlApCOjUD0NBxrMuOJp",
      "duration_ms": 236392,
      "time_signature": 4
    },
    {
      "danceability": 0.396,
      "energy": 0.521,
      "key": 2,
      "loudness": -7.093,
      "mode": 1,
      "speechiness": 0.0312,
      "acousticness": 0.0101,
      "instrumentalness": 0,
      "liveness": 0.884,
      "valence": 0.126,
      "tempo": 135.742,
      "type": "audio_features",
      "id": "1yYUIjT3bZ9RB9vejqYy9f",
      "uri": "spotify:track:1yYUIjT3bZ9RB9vejqYy9f",
      "track_href": "https://api.spotify.com/v1/tracks/1yYUIjT3bZ9RB9vejqYy9f",
      "analysis_url": "https://api.spotify.com/v1/audio-analysis/1yYUIjT3bZ9RB9vejqYy9f",
      "duration_ms": 341080,
      "time_signature": 4
    },
    {
      "danceability": 0.529,
      "energy": 0.375,
      "key": 2,
      "loudness": -10.59,
      "mode": 1,
      "speechiness": 0.0247,
      "acousticness": 0.305,
      "instrumentalness": 3.29e-05,
      "liveness": 0.0861,
      "valence": 0.275,
      "tempo": 136.071,
      "type": "audio_features",
      "id": "601913bnwOH19HblKXMr2d",
      "uri": "spotify:track:601913bnwOH19HblKXMr2d",
      "track_href": "https://api.spotify.com/v1/tracks/601913bnwOH19HblKXMr2d",
      "analysis_url": "https://api.spotify.com/v1/audio-analysis/601913bnwOH19HblKXMr2d",
      "duration_ms": 285307,
      "time_signature": 4
    },
    {
      "danceability": 0.607,
      "energy": 0.671,
      "key": 3,
      "loudness": -5.986,
      "mode": 1,
      "speechiness": 0.0344,
      "acousticness": 0.159,
      "instrumentalness": 0.0038,
      "liveness": 0.117,
      "valence": 0.674,
      "tempo": 150.001,
      "type": "audio_features",
      "id": "3gKm2TjAkLUNpJC1WKOzjX",
      "uri": "spotify:track:3gKm2TjAkLUNpJC1WKOzjX",
      "track_href": "https://api.spotify.com/v1/tracks/3gKm2TjAkLUNpJC1WKOzjX",
      "analysis_url": "https://api.spotify.com/v1/audio-analysis/3gKm2TjAkLUNpJC1WKOzjX",
      "duration_ms": 304427,
      "time_signature": 4
    },
    {
      "danceability": 0.479,
      "energy": 0.872,
      "key": 6,
      "loudness": -3.719,
      "mode": 0,
      "speechiness": 0.0515,
      "acousticness": 0.000733,
      "instrumentalness": 0,
      "liveness": 0.11,
      "valence": 0.208,
      "tempo": 129.886,
      "type": "audio_features",
      "id": "4Ng14pKFvjrLPqI1hgYfIN",
      "uri": "spotify:track:4Ng14pKFvjrLPqI1hgYfIN",
      "track_href": "https://api.spotify.com/v1/tracks/4Ng14pKFvjrLPqI1hgYfIN",
      "analysis_url": "https://api.spotify.com/v1/audio-analysis/4Ng14pKFvjrLPqI1hgYfIN",
      "duration_ms": 293538,
      "time_signature": 4
    },
    {
      "danceability": 0.185,
      "energy": 0.298,
      "key": 9,
      "loudness": -9.698,
      "mode": 0,
      "speechiness": 0.0293,
      "acousticness": 0.796,
      "instrumentalness": 0.825,
      "liveness": 0.243,
      "valence": 0.104,
      "tempo": 86.982,
      "type": "audio_features",
      "id": "24TMaKkgOU8w3HSIhqN643",
      "uri": "spotify:track:24TMaKkgOU8w3HSIhqN643",
      "track_href": "https://api.spotify.com/v1/tracks/24TMaKkgOU8w3HSIhqN643",
      "analysis_url": "https://api.spotify.com/v1/audio-analysis/24TMaKkgOU8w3HSIhqN643",
      "duration_ms": 483360,
      "time_signature": 4
    },
    {
      "danceability": 0.515,
      "energy": 0.675,
      "key": 6,
      "loudness": -4.801,
      "mode": 1,
      "speechiness": 0.0358,
      "acousticness": 0.0356,
      "instrumentalness": 0,
      "liveness": 0.15,
      "valence": 0.216,
      "tempo": 128.14,
      "type": "audio_features",
      "id": "3qU3qxURhxVFJEuPkx0iyl",
      "uri": "spotify:track:3qU3qxURhxVFJEuPkx0iyl",
      "track_href": "https://api.spotify.com/v1/tracks/3qU3qxURhxVFJEuPkx0iyl",
      "analysis_url": "https://api.spotify.com/v1/audio-analysis/3qU3qxURhxVFJEuPkx0iyl",
      "duration_ms": 212813,
      "time_signature": 4
    },
    {
      "danceability": 0.939,
      "energy": 0.742,
      "key": 5,
      "loudness": -5.171,
      "mode": 0,
      "speechiness": 0.0467,
      "acousticness": 0.321,
      "instrumentalness": 0,
      "liveness": 0.107,
      "valence": 0.924,
      "tempo": 118.978,
      "type": "audio_features",
      "id": "2kQuhkFX7uSVepCD3h29g5",
      "uri": "spotify:track:2kQuhkFX7uSVepCD3h29g5",
      "track_href": "https://api.spotify.com/v1/tracks/2kQuhkFX7uSVepCD3h29g5",
      "analysis_url": "https://api.spotify.com/v1/audio-analysis/2kQuhkFX7uSVepCD3h29g5",
      "duration_ms": 212360,
      "time_signature": 4
    },
    {
      "danceability": 0.386,
      "energy": 0.701,
      "key": 7,
      "loudness": -5.993,
      "mode": 1,
      "speechiness": 0.0332,
      "acousticness": 0.14,
      "instrumentalness": 0.000125,
      "liveness": 0.29,
      "valence": 0.483,
      "tempo": 141.245,
      "type": "audio_features",
      "id": "3RwbqrHZwHg3hpe6sOxMpE",
      "uri": "spotify:track:3RwbqrHZwHg3hpe6sOxMpE",
      "track_href": "https://api.spotify.com/v1/tracks/3RwbqrHZwHg3hpe6sOxMpE",
      "analysis_url": "https://api.spotify.com/v1/audio-analysis/3RwbqrHZwHg3hpe6sOxMpE",
      "duration_ms": 339880,
      "time_signature": 4
    },
    {
      "danceability": 0.556,
      "energy": 0.746,
      "key": 10,
      "loudness": -5.851,
      "mode": 0,
      "speechiness": 0.386,
      "acousticness": 0.0859,
      "instrumentalness": 1.2e-06,
      "liveness": 0.292,
      "valence": 0.69,
      "tempo": 169.959,
      "type": "audio_features",
      "id": "74UhLHIZ5d8QL3LuJqyYeV",
      "uri": "spotify:track:74UhLHIZ5d8QL3LuJqyYeV",
      "track_href": "https://api.spotify.com/v1/tracks/74UhLHIZ5d8QL3LuJqyYeV",
      "analysis_url": "https://api.spotify.com/v1/audio-analysis/74UhLHIZ5d8QL3LuJqyYeV",
      "duration_ms": 229133,
      "time_signature": 4
    },
    {
      "danceability": 0.697,
      "energy": 0.412,
      "key": 9,
      "loudness": -14.467,
      "mode": 1,
      "speechiness": 0.0725,
      "acousticness": 0.704,
      "instrumentalness": 0,
      "liveness": 0.125,
      "valence": 0.638,
      "tempo": 139.945,
      "type": "audio_features",
      "id": "47AZCUpitBMJt6Smj9Tww3",
      "uri": "spotify:track:47AZCUpitBMJt6Smj9Tww3",
      "track_href": "https://api.spotify.com/v1/tracks/47AZCUpitBMJt6Smj9Tww3",
      "analysis_url": "https://api.spotify.com/v1/audio-analysis/47AZCUpitBMJt6Smj9Tww3",
      "duration_ms": 245647,
      "time_signature": 4
    },
    {
      "danceability": 0.853,
      "energy": 0.56,
      "key": 1,
      "loudness": -4.961,
      "mode": 1,
      "speechiness": 0.0406,
      "acousticness": 0.013,
      "instrumentalness": 0,
      "liveness": 0.0944,
      "valence": 0.86,
      "tempo": 134.066,
      "type": "audio_features",
      "id": "0KKkJNfGyhkQ5aFogxQAPU",
      "uri": "spotify:track:0KKkJNfGyhkQ5aFogxQAPU",
      "track_href": "https://api.spotify.com/v1/tracks/0KKkJNfGyhkQ5aFogxQAPU",
      "analysis_url": "https://api.spotify.com/v1/audio-analysis/0KKkJNfGyhkQ5aFogxQAPU",
      "duration_ms": 206693,
      "time_signature": 4
    },
    {
      "danceability": 0.658,
      "energy": 0.312,
      "key": 2,
      "loudness": -8.788,
      "mode": 1,
      "speechiness": 0.0276,
      "acousticness": 0.828,
      "instrumentalness": 0,
      "liveness": 0.11,
      "valence": 0.225,
      "tempo": 135.876,
      "type": "audio_features",
      "id": "0S6IRlh2GHZdw25N81hMLe",
      "uri": "spotify:track:0S6IRlh2GHZdw25N81hMLe",
      "track_href": "https://api.spotify.com/v1/tracks/0S6IRlh2GHZdw25N81hMLe",
      "analysis_url": "https://api.spotify.com/v1/audio-analysis/0S6IRlh2GHZdw25N81hMLe",
      "duration_ms": 216733,
      "time_signature": 4
    },
    {
      "danceability": 0.541,
      "energy": 0.818,
      "key": 0,
      "loudness": -5.52,
      "mode": 1,
      "speechiness": 0.0403,
      "acousticness": 0.0224,
      "instrumentalness": 0.00373,
      "liveness": 0.13,
      "valence": 0.209,
      "tempo": 94.979,
      "type": "audio_features",
      "id": "7LNIu9HxiHXaif0cHXY0Qc",
      "uri": "spotify:track:7LNIu9HxiHXaif0cHXY0Qc",
      "track_href": "https://api.spotify.com/v1/tracks/7LNIu9HxiHXaif0cHXY0Qc",
      "analysis_url": "https://api.spotify.com/v1/audio-analysis/7LNIu9HxiHXaif0cHXY0Qc",
      "duration_ms": 226533,
      "time_signature": 4
    },
    {
      "danceability": 0.766,
      "energy": 0.772,
      "key": 0,
      "loudness": -9.362,
      "mode": 1,
      "speechiness": 0.0353,
      "acousticness": 0.403,
      "instrumentalness": 0.0584,
      "liveness": 0.183,
      "valence": 0.919,
      "tempo": 128.168,
      "type": "audio_features",
      "id": "0qi4b1l0eT3jpzeNHeFXDT",
      "uri": "spotify:track:0qi4b1l0eT3jpzeNHeFXDT",
      "track_href": "https://api.spotify.com/v1/tracks/0qi4b1l0eT3jpzeNHeFXDT",
      "analysis_url": "https://api.spotify.com/v1/audio-analysis/0qi4b1l0eT3jpzeNHeFXDT",
      "duration_ms": 220893,
      "time_signature": 4
    },
    {
      "danceability": 0.516,
      "energy": 0.108,
      "key": 2,
      "loudness": -16.231,
      "mode": 1,
      "speechiness": 0.0298,
      "acousticness": 0.815,
      "instrumentalness": 0,
      "liveness": 0.11,
      "valence": 0.288,
      "tempo": 74.914,
      "type": "audio_features",
      "id": "3SEYycG24ujPRnGad41w2E",
      "uri": "spotify:track:3SEYycG24ujPRnGad41w2E",
      "track_href": "https://api.spotify.com/v1/tracks/3SEYycG24ujPRnGad41w2E",
      "analysis_url": "https://api.spotify.com/v1/audio-analysis/3SEYycG24ujPRnGad41w2E",
      "duration_ms": 231293,
      "time_signature": 4
    },
    {
      "danceability": 0.465,
      "energy": 0.686,
      "key": 7,
      "loudness": -5.429,
      "mode": 0,
      "speechiness": 0.0314,
      "acousticness": 0.118,
      "instrumentalness": 0.00218,
      "liveness": 0.0802,
      "valence": 0.318,
      "tempo": 79.017,
      "type": "audio_features",
      "id": "2Ff1GIulzlbOYsOrNB2SSR",
      "uri": "spotify:track:2Ff1GIulzlbOYsOrNB2SSR",
      "track_href": "https://api.spotify.com/v1/tracks/2Ff1GIulzlbOYsOrNB2SSR",
      "analysis_url": "https://api.spotify.com/v1/audio-analysis/2Ff1GIulzlbOYsOrNB2SSR",
      "duration_ms": 223526,
      "time_signature": 4
    },
    {
      "danceability": 0.512,
      "energy": 0.527,
      "key": 5,
      "loudness": -5.775,
      "mode": 1,
      "speechiness": 0.03,
      "acousticness": 0.123,
      "instrumentalness": 0,
      "liveness": 0.119,
      "valence": 0.642,
      "tempo": 134.246,
      "type": "audio_features",
      "id": "0ItYqXnqgIZisK9zr6s00x",
      "uri": "spotify:track:0ItYqXnqgIZisK9zr6s00x",
      "track_href": "https://api.spotify.com/v1/tracks/0ItYqXnqgIZisK9zr6s00x",
      "analysis_url": "https://api.spotify.com/v1/audio-analysis/0ItYqXnqgIZisK9zr6s00x",
      "duration_ms": 346547,
      "time_signature": 4
    },
    {
      "danceability": 0.328,
      "energy": 0.498,
      "key": 4,
      "loudness": -10.898,
      "mode": 0,
      "speechiness": 0.126,
      "acousticness": 0.532,
      "instrumentalness": 7.94e-05,
      "liveness": 0.117,
      "valence": 0.36,
      "tempo": 175.918,
      "type": "audio_features",
      "id": "1cK4JEQqeIc6nQONq7hyYZ",
      "uri": "spotify:track:1cK4JEQqeIc6nQONq7hyYZ",
      "track_href": "https://api.spotify.com/v1/tracks/1cK4JEQqeIc6nQONq7hyYZ",
      "analysis_url": "https://api.spotify.com/v1/audio-analysis/1cK4JEQqeIc6nQONq7hyYZ",
      "duration_ms": 240173,
      "time_signature": 4
    }
  ]
}
